<pkgdesc name='pygtk' version='2.24.0'>
    <subpackage name='skel'/>
    <subpackage name='minimal'/>
    <subpackage name='bin'>
        <file fileout='Python script, ASCII text executable' mode='100644' path='/usr/lib/pygtk/2.0/demos/__init__.py' group='0' owner='0'/>
        <file fileout='ELF 32-bit LSB shared object, Intel 80386, version 1 (SYSV)' mode='100755' path='/usr/lib/python2.7/site-packages/gtk-2.0/pangocairo.so' group='0' owner='0'/>
        <file fileout='ELF 32-bit LSB shared object, Intel 80386, version 1 (SYSV)' mode='100755' path='/usr/lib/python2.7/site-packages/gtk-2.0/atk.so' group='0' owner='0'/>
        <file fileout='ELF 32-bit LSB shared object, Intel 80386, version 1 (SYSV)' mode='100755' path='/usr/lib/python2.7/site-packages/gtk-2.0/gtkunixprint.so' group='0' owner='0'/>
        <file fileout='ELF 32-bit LSB shared object, Intel 80386, version 1 (SYSV)' mode='100755' path='/usr/lib/python2.7/site-packages/gtk-2.0/gtk/_gtk.so' group='0' owner='0'/>
        <file fileout='ELF 32-bit LSB shared object, Intel 80386, version 1 (SYSV)' mode='100755' path='/usr/lib/python2.7/site-packages/gtk-2.0/gtk/glade.so' group='0' owner='0'/>
        <file fileout='ELF 32-bit LSB shared object, Intel 80386, version 1 (SYSV)' mode='100755' path='/usr/lib/python2.7/site-packages/gtk-2.0/pango.so' group='0' owner='0'/>
    </subpackage>
    <subpackage name='doc'>
        <file fileout='gzip compressed data' mode='100644' path='/usr/share/gtk-doc/html/pygtk/class-pangoattribute.html' group='0' owner='0'/>
        <file fileout='gzip compressed data' mode='100644' path='/usr/share/gtk-doc/html/pygtk/class-gdkpixbuf.html' group='0' owner='0'/>
        <file fileout='gzip compressed data' mode='100644' path='/usr/share/gtk-doc/html/pygtk/class-gtkradioaction.html' group='0' owner='0'/>
        <file fileout='gzip compressed data' mode='100644' path='/usr/share/gtk-doc/html/pygtk/class-gtkrecentmanager.html' group='0' owner='0'/>
        <file fileout='gzip compressed data' mode='100644' path='/usr/share/gtk-doc/html/pygtk/class-gtkrange.html' group='0' owner='0'/>
        <file fileout='gzip compressed data' mode='100644' path='/usr/share/gtk-doc/html/pygtk/class-gtkaccelgroup.html' group='0' owner='0'/>
        <file fileout='gzip compressed data' mode='100644' path='/usr/share/gtk-doc/html/pygtk/class-gdkvisual.html' group='0' owner='0'/>
        <file fileout='gzip compressed data' mode='100644' path='/usr/share/gtk-doc/html/pygtk/class-gtkhscale.html' group='0' owner='0'/>
        <file fileout='gzip compressed data' mode='100644' path='/usr/share/gtk-doc/html/pygtk/class-gtkprogressbar.html' group='0' owner='0'/>
        <file fileout='gzip compressed data' mode='100644' path='/usr/share/gtk-doc/html/pygtk/class-gtkinputdialog.html' group='0' owner='0'/>
        <file fileout='gzip compressed data' mode='100644' path='/usr/share/gtk-doc/html/pygtk/pygtk.devhelp' group='0' owner='0'/>
        <file fileout='gzip compressed data' mode='100644' path='/usr/share/gtk-doc/html/pygtk/class-gtktooltips.html' group='0' owner='0'/>
        <file fileout='gzip compressed data' mode='100644' path='/usr/share/gtk-doc/html/pygtk/class-pangoattriterator.html' group='0' owner='0'/>
        <file fileout='gzip compressed data' mode='100644' path='/usr/share/gtk-doc/html/pygtk/class-gtkpagesetupunixdialog.html' group='0' owner='0'/>
        <file fileout='gzip compressed data' mode='100644' path='/usr/share/gtk-doc/html/pygtk/class-gtktreesortable.html' group='0' owner='0'/>
        <file fileout='gzip compressed data' mode='100644' path='/usr/share/gtk-doc/html/pygtk/class-gtkradiobutton.html' group='0' owner='0'/>
        <file fileout='gzip compressed data' mode='100644' path='/usr/share/gtk-doc/html/pygtk/class-gtkrcstyle.html' group='0' owner='0'/>
        <file fileout='gzip compressed data' mode='100644' path='/usr/share/gtk-doc/html/pygtk/class-gtkaccelmap.html' group='0' owner='0'/>
        <file fileout='gzip compressed data' mode='100644' path='/usr/share/gtk-doc/html/pygtk/class-gtkhbuttonbox.html' group='0' owner='0'/>
        <file fileout='gzip compressed data' mode='100644' path='/usr/share/gtk-doc/html/pygtk/class-gtkfontselectiondialog.html' group='0' owner='0'/>
        <file fileout='gzip compressed data' mode='100644' path='/usr/share/gtk-doc/html/pygtk/class-gtkeventbox.html' group='0' owner='0'/>
        <file fileout='gzip compressed data' mode='100644' path='/usr/share/gtk-doc/html/pygtk/class-gdkdisplay.html' group='0' owner='0'/>
        <file fileout='gzip compressed data' mode='100644' path='/usr/share/gtk-doc/html/pygtk/class-gtkrecentchooser.html' group='0' owner='0'/>
        <file fileout='gzip compressed data' mode='100644' path='/usr/share/gtk-doc/html/pygtk/class-gtkviewport.html' group='0' owner='0'/>
        <file fileout='gzip compressed data' mode='100644' path='/usr/share/gtk-doc/html/pygtk/class-gtkfontselection.html' group='0' owner='0'/>
        <file fileout='gzip compressed data' mode='100644' path='/usr/share/gtk-doc/html/pygtk/class-gtkwindow.html' group='0' owner='0'/>
        <file fileout='gzip compressed data' mode='100644' path='/usr/share/gtk-doc/html/pygtk/class-gtkimcontext.html' group='0' owner='0'/>
        <file fileout='gzip compressed data' mode='100644' path='/usr/share/gtk-doc/html/pygtk/class-atkcomponent.html' group='0' owner='0'/>
        <file fileout='gzip compressed data' mode='100644' path='/usr/share/gtk-doc/html/pygtk/class-gtkliststore.html' group='0' owner='0'/>
        <file fileout='gzip compressed data' mode='100644' path='/usr/share/gtk-doc/html/pygtk/class-gdkpangorenderer.html' group='0' owner='0'/>
        <file fileout='gzip compressed data' mode='100644' path='/usr/share/gtk-doc/html/pygtk/class-gtkruler.html' group='0' owner='0'/>
        <file fileout='gzip compressed data' mode='100644' path='/usr/share/gtk-doc/html/pygtk/class-gtktexttag.html' group='0' owner='0'/>
        <file fileout='gzip compressed data' mode='100644' path='/usr/share/gtk-doc/html/pygtk/class-gtktreemodelfilter.html' group='0' owner='0'/>
        <file fileout='gzip compressed data' mode='100644' path='/usr/share/gtk-doc/html/pygtk/class-gtkmenu.html' group='0' owner='0'/>
        <file fileout='gzip compressed data' mode='100644' path='/usr/share/gtk-doc/html/pygtk/class-atkobjectfactory.html' group='0' owner='0'/>
        <file fileout='gzip compressed data' mode='100644' path='/usr/share/gtk-doc/html/pygtk/class-gdkapplaunchcontext.html' group='0' owner='0'/>
        <file fileout='gzip compressed data' mode='100644' path='/usr/share/gtk-doc/html/pygtk/class-gtkprintunixdialog.html' group='0' owner='0'/>
        <file fileout='gzip compressed data' mode='100644' path='/usr/share/gtk-doc/html/pygtk/class-gdkdisplaymanager.html' group='0' owner='0'/>
        <file fileout='gzip compressed data' mode='100644' path='/usr/share/gtk-doc/html/pygtk/class-gtkaspectframe.html' group='0' owner='0'/>
        <file fileout='gzip compressed data' mode='100644' path='/usr/share/gtk-doc/html/pygtk/class-gtkimage.html' group='0' owner='0'/>
        <file fileout='gzip compressed data' mode='100644' path='/usr/share/gtk-doc/html/pygtk/class-atkdocument.html' group='0' owner='0'/>
        <file fileout='gzip compressed data' mode='100644' path='/usr/share/gtk-doc/html/pygtk/class-gdkdragcontext.html' group='0' owner='0'/>
        <file fileout='gzip compressed data' mode='100644' path='/usr/share/gtk-doc/html/pygtk/class-gtkimagemenuitem.html' group='0' owner='0'/>
        <file fileout='gzip compressed data' mode='100644' path='/usr/share/gtk-doc/html/pygtk/pango-constants.html' group='0' owner='0'/>
        <file fileout='gzip compressed data' mode='100644' path='/usr/share/gtk-doc/html/pygtk/class-gtkcombobox.html' group='0' owner='0'/>
        <file fileout='gzip compressed data' mode='100644' path='/usr/share/gtk-doc/html/pygtk/class-gtkfilechooserwidget.html' group='0' owner='0'/>
        <file fileout='gzip compressed data' mode='100644' path='/usr/share/gtk-doc/html/pygtk/class-gtkvolumebutton.html' group='0' owner='0'/>
        <file fileout='gzip compressed data' mode='100644' path='/usr/share/gtk-doc/html/pygtk/class-gtkcombo.html' group='0' owner='0'/>
        <file fileout='gzip compressed data' mode='100644' path='/usr/share/gtk-doc/html/pygtk/class-gtkoptionmenu.html' group='0' owner='0'/>
        <file fileout='gzip compressed data' mode='100644' path='/usr/share/gtk-doc/html/pygtk/gtk-constants.html' group='0' owner='0'/>
        <file fileout='gzip compressed data' mode='100644' path='/usr/share/gtk-doc/html/pygtk/class-gtkscalebutton.html' group='0' owner='0'/>
        <file fileout='gzip compressed data' mode='100644' path='/usr/share/gtk-doc/html/pygtk/class-gtktogglebutton.html' group='0' owner='0'/>
        <file fileout='gzip compressed data' mode='100644' path='/usr/share/gtk-doc/html/pygtk/class-gdkatom.html' group='0' owner='0'/>
        <file fileout='gzip compressed data' mode='100644' path='/usr/share/gtk-doc/html/pygtk/class-pangofontdescription.html' group='0' owner='0'/>
        <file fileout='gzip compressed data' mode='100644' path='/usr/share/gtk-doc/html/pygtk/class-gtkscrollbar.html' group='0' owner='0'/>
        <file fileout='gzip compressed data' mode='100644' path='/usr/share/gtk-doc/html/pygtk/class-gtkfixed.html' group='0' owner='0'/>
        <file fileout='gzip compressed data' mode='100644' path='/usr/share/gtk-doc/html/pygtk/class-atktext.html' group='0' owner='0'/>
        <file fileout='gzip compressed data' mode='100644' path='/usr/share/gtk-doc/html/pygtk/cursors/ur_angle.png' group='0' owner='0'/>
        <file fileout='gzip compressed data' mode='100644' path='/usr/share/gtk-doc/html/pygtk/cursors/gumby.png' group='0' owner='0'/>
        <file fileout='gzip compressed data' mode='100644' path='/usr/share/gtk-doc/html/pygtk/cursors/right_tee.png' group='0' owner='0'/>
        <file fileout='gzip compressed data' mode='100644' path='/usr/share/gtk-doc/html/pygtk/cursors/X_cursor.png' group='0' owner='0'/>
        <file fileout='gzip compressed data' mode='100644' path='/usr/share/gtk-doc/html/pygtk/cursors/circle.png' group='0' owner='0'/>
        <file fileout='gzip compressed data' mode='100644' path='/usr/share/gtk-doc/html/pygtk/cursors/bogosity.png' group='0' owner='0'/>
        <file fileout='gzip compressed data' mode='100644' path='/usr/share/gtk-doc/html/pygtk/cursors/center_ptr.png' group='0' owner='0'/>
        <file fileout='gzip compressed data' mode='100644' path='/usr/share/gtk-doc/html/pygtk/cursors/star.png' group='0' owner='0'/>
        <file fileout='gzip compressed data' mode='100644' path='/usr/share/gtk-doc/html/pygtk/cursors/middlebutton.png' group='0' owner='0'/>
        <file fileout='gzip compressed data' mode='100644' path='/usr/share/gtk-doc/html/pygtk/cursors/rtl_logo.png' group='0' owner='0'/>
        <file fileout='gzip compressed data' mode='100644' path='/usr/share/gtk-doc/html/pygtk/cursors/left_side.png' group='0' owner='0'/>
        <file fileout='gzip compressed data' mode='100644' path='/usr/share/gtk-doc/html/pygtk/cursors/left_ptr.png' group='0' owner='0'/>
        <file fileout='gzip compressed data' mode='100644' path='/usr/share/gtk-doc/html/pygtk/cursors/crosshair.png' group='0' owner='0'/>
        <file fileout='gzip compressed data' mode='100644' path='/usr/share/gtk-doc/html/pygtk/cursors/heart.png' group='0' owner='0'/>
        <file fileout='gzip compressed data' mode='100644' path='/usr/share/gtk-doc/html/pygtk/cursors/right_side.png' group='0' owner='0'/>
        <file fileout='gzip compressed data' mode='100644' path='/usr/share/gtk-doc/html/pygtk/cursors/dot.png' group='0' owner='0'/>
        <file fileout='gzip compressed data' mode='100644' path='/usr/share/gtk-doc/html/pygtk/cursors/sizing.png' group='0' owner='0'/>
        <file fileout='gzip compressed data' mode='100644' path='/usr/share/gtk-doc/html/pygtk/cursors/spraycan.png' group='0' owner='0'/>
        <file fileout='gzip compressed data' mode='100644' path='/usr/share/gtk-doc/html/pygtk/cursors/dotbox.png' group='0' owner='0'/>
        <file fileout='gzip compressed data' mode='100644' path='/usr/share/gtk-doc/html/pygtk/cursors/cross_reverse.png' group='0' owner='0'/>
        <file fileout='gzip compressed data' mode='100644' path='/usr/share/gtk-doc/html/pygtk/cursors/boat.png' group='0' owner='0'/>
        <file fileout='gzip compressed data' mode='100644' path='/usr/share/gtk-doc/html/pygtk/cursors/ll_angle.png' group='0' owner='0'/>
        <file fileout='gzip compressed data' mode='100644' path='/usr/share/gtk-doc/html/pygtk/cursors/arrow.png' group='0' owner='0'/>
        <file fileout='gzip compressed data' mode='100644' path='/usr/share/gtk-doc/html/pygtk/cursors/draft_large.png' group='0' owner='0'/>
        <file fileout='gzip compressed data' mode='100644' path='/usr/share/gtk-doc/html/pygtk/cursors/shuttle.png' group='0' owner='0'/>
        <file fileout='gzip compressed data' mode='100644' path='/usr/share/gtk-doc/html/pygtk/cursors/pencil.png' group='0' owner='0'/>
        <file fileout='gzip compressed data' mode='100644' path='/usr/share/gtk-doc/html/pygtk/cursors/coffee_mug.png' group='0' owner='0'/>
        <file fileout='gzip compressed data' mode='100644' path='/usr/share/gtk-doc/html/pygtk/cursors/iron_cross.png' group='0' owner='0'/>
        <file fileout='gzip compressed data' mode='100644' path='/usr/share/gtk-doc/html/pygtk/cursors/question_arrow.png' group='0' owner='0'/>
        <file fileout='gzip compressed data' mode='100644' path='/usr/share/gtk-doc/html/pygtk/cursors/sb_down_arrow.png' group='0' owner='0'/>
        <file fileout='gzip compressed data' mode='100644' path='/usr/share/gtk-doc/html/pygtk/cursors/hand1.png' group='0' owner='0'/>
        <file fileout='gzip compressed data' mode='100644' path='/usr/share/gtk-doc/html/pygtk/cursors/based_arrow_up.png' group='0' owner='0'/>
        <file fileout='gzip compressed data' mode='100644' path='/usr/share/gtk-doc/html/pygtk/cursors/pirate.png' group='0' owner='0'/>
        <file fileout='gzip compressed data' mode='100644' path='/usr/share/gtk-doc/html/pygtk/cursors/rightbutton.png' group='0' owner='0'/>
        <file fileout='gzip compressed data' mode='100644' path='/usr/share/gtk-doc/html/pygtk/cursors/draft_small.png' group='0' owner='0'/>
        <file fileout='gzip compressed data' mode='100644' path='/usr/share/gtk-doc/html/pygtk/cursors/plus.png' group='0' owner='0'/>
        <file fileout='gzip compressed data' mode='100644' path='/usr/share/gtk-doc/html/pygtk/cursors/spider.png' group='0' owner='0'/>
        <file fileout='gzip compressed data' mode='100644' path='/usr/share/gtk-doc/html/pygtk/cursors/right_ptr.png' group='0' owner='0'/>
        <file fileout='gzip compressed data' mode='100644' path='/usr/share/gtk-doc/html/pygtk/cursors/sailboat.png' group='0' owner='0'/>
        <file fileout='gzip compressed data' mode='100644' path='/usr/share/gtk-doc/html/pygtk/cursors/diamond_cross.png' group='0' owner='0'/>
        <file fileout='gzip compressed data' mode='100644' path='/usr/share/gtk-doc/html/pygtk/cursors/top_left_corner.png' group='0' owner='0'/>
        <file fileout='gzip compressed data' mode='100644' path='/usr/share/gtk-doc/html/pygtk/cursors/bottom_right_corner.png' group='0' owner='0'/>
        <file fileout='gzip compressed data' mode='100644' path='/usr/share/gtk-doc/html/pygtk/cursors/clock.png' group='0' owner='0'/>
        <file fileout='gzip compressed data' mode='100644' path='/usr/share/gtk-doc/html/pygtk/cursors/sb_left_arrow.png' group='0' owner='0'/>
        <file fileout='gzip compressed data' mode='100644' path='/usr/share/gtk-doc/html/pygtk/cursors/exchange.png' group='0' owner='0'/>
        <file fileout='gzip compressed data' mode='100644' path='/usr/share/gtk-doc/html/pygtk/cursors/mouse.png' group='0' owner='0'/>
        <file fileout='gzip compressed data' mode='100644' path='/usr/share/gtk-doc/html/pygtk/cursors/ul_angle.png' group='0' owner='0'/>
        <file fileout='gzip compressed data' mode='100644' path='/usr/share/gtk-doc/html/pygtk/cursors/top_right_corner.png' group='0' owner='0'/>
        <file fileout='gzip compressed data' mode='100644' path='/usr/share/gtk-doc/html/pygtk/cursors/top_side.png' group='0' owner='0'/>
        <file fileout='gzip compressed data' mode='100644' path='/usr/share/gtk-doc/html/pygtk/cursors/gobbler.png' group='0' owner='0'/>
        <file fileout='gzip compressed data' mode='100644' path='/usr/share/gtk-doc/html/pygtk/cursors/sb_h_double_arrow.png' group='0' owner='0'/>
        <file fileout='gzip compressed data' mode='100644' path='/usr/share/gtk-doc/html/pygtk/cursors/box_spiral.png' group='0' owner='0'/>
        <file fileout='gzip compressed data' mode='100644' path='/usr/share/gtk-doc/html/pygtk/cursors/lr_angle.png' group='0' owner='0'/>
        <file fileout='gzip compressed data' mode='100644' path='/usr/share/gtk-doc/html/pygtk/cursors/double_arrow.png' group='0' owner='0'/>
        <file fileout='gzip compressed data' mode='100644' path='/usr/share/gtk-doc/html/pygtk/cursors/cross.png' group='0' owner='0'/>
        <file fileout='gzip compressed data' mode='100644' path='/usr/share/gtk-doc/html/pygtk/cursors/sb_right_arrow.png' group='0' owner='0'/>
        <file fileout='gzip compressed data' mode='100644' path='/usr/share/gtk-doc/html/pygtk/cursors/bottom_side.png' group='0' owner='0'/>
        <file fileout='gzip compressed data' mode='100644' path='/usr/share/gtk-doc/html/pygtk/cursors/watch.png' group='0' owner='0'/>
        <file fileout='gzip compressed data' mode='100644' path='/usr/share/gtk-doc/html/pygtk/cursors/top_tee.png' group='0' owner='0'/>
        <file fileout='gzip compressed data' mode='100644' path='/usr/share/gtk-doc/html/pygtk/cursors/based_arrow_down.png' group='0' owner='0'/>
        <file fileout='gzip compressed data' mode='100644' path='/usr/share/gtk-doc/html/pygtk/cursors/draped_box.png' group='0' owner='0'/>
        <file fileout='gzip compressed data' mode='100644' path='/usr/share/gtk-doc/html/pygtk/cursors/sb_v_double_arrow.png' group='0' owner='0'/>
        <file fileout='gzip compressed data' mode='100644' path='/usr/share/gtk-doc/html/pygtk/cursors/tcross.png' group='0' owner='0'/>
        <file fileout='gzip compressed data' mode='100644' path='/usr/share/gtk-doc/html/pygtk/cursors/umbrella.png' group='0' owner='0'/>
        <file fileout='gzip compressed data' mode='100644' path='/usr/share/gtk-doc/html/pygtk/cursors/trek.png' group='0' owner='0'/>
        <file fileout='gzip compressed data' mode='100644' path='/usr/share/gtk-doc/html/pygtk/cursors/left_tee.png' group='0' owner='0'/>
        <file fileout='gzip compressed data' mode='100644' path='/usr/share/gtk-doc/html/pygtk/cursors/sb_up_arrow.png' group='0' owner='0'/>
        <file fileout='gzip compressed data' mode='100644' path='/usr/share/gtk-doc/html/pygtk/cursors/bottom_tee.png' group='0' owner='0'/>
        <file fileout='gzip compressed data' mode='100644' path='/usr/share/gtk-doc/html/pygtk/cursors/man.png' group='0' owner='0'/>
        <file fileout='gzip compressed data' mode='100644' path='/usr/share/gtk-doc/html/pygtk/cursors/xterm.png' group='0' owner='0'/>
        <file fileout='gzip compressed data' mode='100644' path='/usr/share/gtk-doc/html/pygtk/cursors/top_left_arrow.png' group='0' owner='0'/>
        <file fileout='gzip compressed data' mode='100644' path='/usr/share/gtk-doc/html/pygtk/cursors/leftbutton.png' group='0' owner='0'/>
        <file fileout='gzip compressed data' mode='100644' path='/usr/share/gtk-doc/html/pygtk/cursors/target.png' group='0' owner='0'/>
        <file fileout='gzip compressed data' mode='100644' path='/usr/share/gtk-doc/html/pygtk/cursors/hand2.png' group='0' owner='0'/>
        <file fileout='gzip compressed data' mode='100644' path='/usr/share/gtk-doc/html/pygtk/cursors/icon.png' group='0' owner='0'/>
        <file fileout='gzip compressed data' mode='100644' path='/usr/share/gtk-doc/html/pygtk/cursors/bottom_left_corner.png' group='0' owner='0'/>
        <file fileout='gzip compressed data' mode='100644' path='/usr/share/gtk-doc/html/pygtk/cursors/fleur.png' group='0' owner='0'/>
        <file fileout='gzip compressed data' mode='100644' path='/usr/share/gtk-doc/html/pygtk/class-gtkstatusbar.html' group='0' owner='0'/>
        <file fileout='gzip compressed data' mode='100644' path='/usr/share/gtk-doc/html/pygtk/class-gtkprintcontext.html' group='0' owner='0'/>
        <file fileout='gzip compressed data' mode='100644' path='/usr/share/gtk-doc/html/pygtk/class-gtktreedragsource.html' group='0' owner='0'/>
        <file fileout='gzip compressed data' mode='100644' path='/usr/share/gtk-doc/html/pygtk/class-atkvalue.html' group='0' owner='0'/>
        <file fileout='gzip compressed data' mode='100644' path='/usr/share/gtk-doc/html/pygtk/class-pangofontsetsimple.html' group='0' owner='0'/>
        <file fileout='gzip compressed data' mode='100644' path='/usr/share/gtk-doc/html/pygtk/unixprint-constants.html' group='0' owner='0'/>
        <file fileout='gzip compressed data' mode='100644' path='/usr/share/gtk-doc/html/pygtk/class-pangorenderer.html' group='0' owner='0'/>
        <file fileout='gzip compressed data' mode='100644' path='/usr/share/gtk-doc/html/pygtk/pangocairo-constants.html' group='0' owner='0'/>
        <file fileout='gzip compressed data' mode='100644' path='/usr/share/gtk-doc/html/pygtk/class-gtkcelllayout.html' group='0' owner='0'/>
        <file fileout='gzip compressed data' mode='100644' path='/usr/share/gtk-doc/html/pygtk/class-gtkmisc.html' group='0' owner='0'/>
        <file fileout='gzip compressed data' mode='100644' path='/usr/share/gtk-doc/html/pygtk/class-gtkcheckbutton.html' group='0' owner='0'/>
        <file fileout='gzip compressed data' mode='100644' path='/usr/share/gtk-doc/html/pygtk/class-pygtkgenerictreemodel.html' group='0' owner='0'/>
        <file fileout='gzip compressed data' mode='100644' path='/usr/share/gtk-doc/html/pygtk/class-gtkprintsettings.html' group='0' owner='0'/>
        <file fileout='gzip compressed data' mode='100644' path='/usr/share/gtk-doc/html/pygtk/class-gtkrecentchooserwidget.html' group='0' owner='0'/>
        <file fileout='gzip compressed data' mode='100644' path='/usr/share/gtk-doc/html/pygtk/class-gtktoolshell.html' group='0' owner='0'/>
        <file fileout='gzip compressed data' mode='100644' path='/usr/share/gtk-doc/html/pygtk/class-gtkimcontextsimple.html' group='0' owner='0'/>
        <file fileout='gzip compressed data' mode='100644' path='/usr/share/gtk-doc/html/pygtk/class-gtkfontbutton.html' group='0' owner='0'/>
        <file fileout='gzip compressed data' mode='100644' path='/usr/share/gtk-doc/html/pygtk/class-gtkwindowgroup.html' group='0' owner='0'/>
        <file fileout='gzip compressed data' mode='100644' path='/usr/share/gtk-doc/html/pygtk/class-gtkuimanager.html' group='0' owner='0'/>
        <file fileout='gzip compressed data' mode='100644' path='/usr/share/gtk-doc/html/pygtk/class-gtknotebook.html' group='0' owner='0'/>
        <file fileout='gzip compressed data' mode='100644' path='/usr/share/gtk-doc/html/pygtk/class-gtkvscrollbar.html' group='0' owner='0'/>
        <file fileout='gzip compressed data' mode='100644' path='/usr/share/gtk-doc/html/pygtk/class-atkrelationset.html' group='0' owner='0'/>
        <file fileout='gzip compressed data' mode='100644' path='/usr/share/gtk-doc/html/pygtk/class-gtkcellrenderertext.html' group='0' owner='0'/>
        <file fileout='gzip compressed data' mode='100644' path='/usr/share/gtk-doc/html/pygtk/class-gtkmountoperation.html' group='0' owner='0'/>
        <file fileout='gzip compressed data' mode='100644' path='/usr/share/gtk-doc/html/pygtk/class-gtktreemodelsort.html' group='0' owner='0'/>
        <file fileout='gzip compressed data' mode='100644' path='/usr/share/gtk-doc/html/pygtk/class-pangofontmap.html' group='0' owner='0'/>
        <file mode='100644' path='/usr/share/gtk-doc/html/pygtk/class-gtkinfobar.html' group='0' owner='0'/>
        <file fileout='gzip compressed data' mode='100644' path='/usr/share/gtk-doc/html/pygtk/class-gtkinvisible.html' group='0' owner='0'/>
        <file fileout='gzip compressed data' mode='100644' path='/usr/share/gtk-doc/html/pygtk/class-gtkclipboard.html' group='0' owner='0'/>
        <file fileout='gzip compressed data' mode='100644' path='/usr/share/gtk-doc/html/pygtk/class-pangofontset.html' group='0' owner='0'/>
        <file fileout='gzip compressed data' mode='100644' path='/usr/share/gtk-doc/html/pygtk/class-gtkiconfactory.html' group='0' owner='0'/>
        <file fileout='gzip compressed data' mode='100644' path='/usr/share/gtk-doc/html/pygtk/class-gdkdrawable.html' group='0' owner='0'/>
        <file fileout='gzip compressed data' mode='100644' path='/usr/share/gtk-doc/html/pygtk/pygtk-introduction.html' group='0' owner='0'/>
        <file fileout='gzip compressed data' mode='100644' path='/usr/share/gtk-doc/html/pygtk/class-pangolayoutline.html' group='0' owner='0'/>
        <file fileout='gzip compressed data' mode='100644' path='/usr/share/gtk-doc/html/pygtk/class-gtkbuilder.html' group='0' owner='0'/>
        <file mode='100644' path='/usr/share/gtk-doc/html/pygtk/class-gtkcomboboxtext.html' group='0' owner='0'/>
        <file mode='100644' path='/usr/share/gtk-doc/html/pygtk/class-gtkcellrendererspinner.html' group='0' owner='0'/>
        <file fileout='gzip compressed data' mode='100644' path='/usr/share/gtk-doc/html/pygtk/class-atkgobjectaccessible.html' group='0' owner='0'/>
        <file fileout='gzip compressed data' mode='100644' path='/usr/share/gtk-doc/html/pygtk/class-pangofontfamily.html' group='0' owner='0'/>
        <file fileout='gzip compressed data' mode='100644' path='/usr/share/gtk-doc/html/pygtk/gdk-functions.html' group='0' owner='0'/>
        <file fileout='gzip compressed data' mode='100644' path='/usr/share/gtk-doc/html/pygtk/class-gtkpaned.html' group='0' owner='0'/>
        <file fileout='gzip compressed data' mode='100644' path='/usr/share/gtk-doc/html/pygtk/class-gtktable.html' group='0' owner='0'/>
        <file fileout='gzip compressed data' mode='100644' path='/usr/share/gtk-doc/html/pygtk/class-gtktreestore.html' group='0' owner='0'/>
        <file fileout='gzip compressed data' mode='100644' path='/usr/share/gtk-doc/html/pygtk/class-gtkradiomenuitem.html' group='0' owner='0'/>
        <file fileout='gzip compressed data' mode='100644' path='/usr/share/gtk-doc/html/pygtk/atk-class-reference.html' group='0' owner='0'/>
        <file fileout='gzip compressed data' mode='100644' path='/usr/share/gtk-doc/html/pygtk/class-gdkpixbufanimationiter.html' group='0' owner='0'/>
        <file fileout='gzip compressed data' mode='100644' path='/usr/share/gtk-doc/html/pygtk/class-gtkselectiondata.html' group='0' owner='0'/>
        <file fileout='gzip compressed data' mode='100644' path='/usr/share/gtk-doc/html/pygtk/class-gtkfilechooserdialog.html' group='0' owner='0'/>
        <file fileout='gzip compressed data' mode='100644' path='/usr/share/gtk-doc/html/pygtk/class-atkhyperlink.html' group='0' owner='0'/>
        <file fileout='gzip compressed data' mode='100644' path='/usr/share/gtk-doc/html/pygtk/class-gtkmenushell.html' group='0' owner='0'/>
        <file fileout='gzip compressed data' mode='100644' path='/usr/share/gtk-doc/html/pygtk/class-gtkaccellabel.html' group='0' owner='0'/>
        <file fileout='gzip compressed data' mode='100644' path='/usr/share/gtk-doc/html/pygtk/class-gtkfilechooserbutton.html' group='0' owner='0'/>
        <file fileout='gzip compressed data' mode='100644' path='/usr/share/gtk-doc/html/pygtk/class-gtkcellrendererspin.html' group='0' owner='0'/>
        <file fileout='gzip compressed data' mode='100644' path='/usr/share/gtk-doc/html/pygtk/class-atkeditabletext.html' group='0' owner='0'/>
        <file fileout='gzip compressed data' mode='100644' path='/usr/share/gtk-doc/html/pygtk/class-gtkscrolledwindow.html' group='0' owner='0'/>
        <file fileout='gzip compressed data' mode='100644' path='/usr/share/gtk-doc/html/pygtk/class-gtkitem.html' group='0' owner='0'/>
        <file fileout='gzip compressed data' mode='100644' path='/usr/share/gtk-doc/html/pygtk/class-gtktextbuffer.html' group='0' owner='0'/>
        <file fileout='gzip compressed data' mode='100644' path='/usr/share/gtk-doc/html/pygtk/class-gtktextmark.html' group='0' owner='0'/>
        <file fileout='gzip compressed data' mode='100644' path='/usr/share/gtk-doc/html/pygtk/class-gtkvpaned.html' group='0' owner='0'/>
        <file fileout='gzip compressed data' mode='100644' path='/usr/share/gtk-doc/html/pygtk/class-gtkmenuitem.html' group='0' owner='0'/>
        <file fileout='gzip compressed data' mode='100644' path='/usr/share/gtk-doc/html/pygtk/class-gtkdrawingarea.html' group='0' owner='0'/>
        <file fileout='gzip compressed data' mode='100644' path='/usr/share/gtk-doc/html/pygtk/class-gtkalignment.html' group='0' owner='0'/>
        <file fileout='gzip compressed data' mode='100644' path='/usr/share/gtk-doc/html/pygtk/class-gtktoolitem.html' group='0' owner='0'/>
        <file fileout='gzip compressed data' mode='100644' path='/usr/share/gtk-doc/html/pygtk/class-gtktreeselection.html' group='0' owner='0'/>
        <file fileout='gzip compressed data' mode='100644' path='/usr/share/gtk-doc/html/pygtk/class-gtkhscrollbar.html' group='0' owner='0'/>
        <file fileout='gzip compressed data' mode='100644' path='/usr/share/gtk-doc/html/pygtk/class-gdkgc.html' group='0' owner='0'/>
        <file fileout='gzip compressed data' mode='100644' path='/usr/share/gtk-doc/html/pygtk/index.html' group='0' owner='0'/>
        <file fileout='gzip compressed data' mode='100644' path='/usr/share/gtk-doc/html/pygtk/class-atktable.html' group='0' owner='0'/>
        <file fileout='gzip compressed data' mode='100644' path='/usr/share/gtk-doc/html/pygtk/class-gtkiconinfo.html' group='0' owner='0'/>
        <file fileout='gzip compressed data' mode='100644' path='/usr/share/gtk-doc/html/pygtk/class-gtkdialog.html' group='0' owner='0'/>
        <file fileout='gzip compressed data' mode='100644' path='/usr/share/gtk-doc/html/pygtk/class-pangolayout.html' group='0' owner='0'/>
        <file fileout='gzip compressed data' mode='100644' path='/usr/share/gtk-doc/html/pygtk/class-gtkiconset.html' group='0' owner='0'/>
        <file fileout='gzip compressed data' mode='100644' path='/usr/share/gtk-doc/html/pygtk/gtk-functions.html' group='0' owner='0'/>
        <file fileout='gzip compressed data' mode='100644' path='/usr/share/gtk-doc/html/pygtk/class-atkhypertext.html' group='0' owner='0'/>
        <file fileout='gzip compressed data' mode='100644' path='/usr/share/gtk-doc/html/pygtk/class-gtktextview.html' group='0' owner='0'/>
        <file fileout='gzip compressed data' mode='100644' path='/usr/share/gtk-doc/html/pygtk/class-gtkiconview.html' group='0' owner='0'/>
        <file fileout='gzip compressed data' mode='100644' path='/usr/share/gtk-doc/html/pygtk/class-pangocairocairofontmap.html' group='0' owner='0'/>
        <file fileout='gzip compressed data' mode='100644' path='/usr/share/gtk-doc/html/pygtk/class-gtkiconsource.html' group='0' owner='0'/>
        <file fileout='gzip compressed data' mode='100644' path='/usr/share/gtk-doc/html/pygtk/atk-constants.html' group='0' owner='0'/>
        <file mode='100644' path='/usr/share/gtk-doc/html/pygtk/class-gtkoffscreenwindow.html' group='0' owner='0'/>
        <file fileout='gzip compressed data' mode='100644' path='/usr/share/gtk-doc/html/pygtk/class-gtkfilefilter.html' group='0' owner='0'/>
        <file fileout='gzip compressed data' mode='100644' path='/usr/share/gtk-doc/html/pygtk/class-atkregistry.html' group='0' owner='0'/>
        <file fileout='gzip compressed data' mode='100644' path='/usr/share/gtk-doc/html/pygtk/class-atkimplementor.html' group='0' owner='0'/>
        <file fileout='gzip compressed data' mode='100644' path='/usr/share/gtk-doc/html/pygtk/class-pygtktreemodelrow.html' group='0' owner='0'/>
        <file fileout='gzip compressed data' mode='100644' path='/usr/share/gtk-doc/html/pygtk/index.sgml' group='0' owner='0'/>
        <file fileout='gzip compressed data' mode='100644' path='/usr/share/gtk-doc/html/pygtk/class-gtkborder.html' group='0' owner='0'/>
        <file fileout='gzip compressed data' mode='100644' path='/usr/share/gtk-doc/html/pygtk/class-gtkadjustment.html' group='0' owner='0'/>
        <file fileout='gzip compressed data' mode='100644' path='/usr/share/gtk-doc/html/pygtk/unixprint-class-reference.html' group='0' owner='0'/>
        <file fileout='gzip compressed data' mode='100644' path='/usr/share/gtk-doc/html/pygtk/class-gtkprintoperation.html' group='0' owner='0'/>
        <file fileout='gzip compressed data' mode='100644' path='/usr/share/gtk-doc/html/pygtk/class-gtkrecentchooserdialog.html' group='0' owner='0'/>
        <file fileout='gzip compressed data' mode='100644' path='/usr/share/gtk-doc/html/pygtk/class-pangoglyphstring.html' group='0' owner='0'/>
        <file fileout='gzip compressed data' mode='100644' path='/usr/share/gtk-doc/html/pygtk/class-gtkcellrenderercombo.html' group='0' owner='0'/>
        <file fileout='gzip compressed data' mode='100644' path='/usr/share/gtk-doc/html/pygtk/class-gtkvbox.html' group='0' owner='0'/>
        <file fileout='gzip compressed data' mode='100644' path='/usr/share/gtk-doc/html/pygtk/class-gtkaccessible.html' group='0' owner='0'/>
        <file fileout='gzip compressed data' mode='100644' path='/usr/share/gtk-doc/html/pygtk/class-gtksettings.html' group='0' owner='0'/>
        <file fileout='gzip compressed data' mode='100644' path='/usr/share/gtk-doc/html/pygtk/class-gtkcellview.html' group='0' owner='0'/>
        <file fileout='gzip compressed data' mode='100644' path='/usr/share/gtk-doc/html/pygtk/class-pangofontface.html' group='0' owner='0'/>
        <file fileout='gzip compressed data' mode='100644' path='/usr/share/gtk-doc/html/pygtk/class-gtkassistant.html' group='0' owner='0'/>
        <file fileout='gzip compressed data' mode='100644' path='/usr/share/gtk-doc/html/pygtk/class-gtkseparator.html' group='0' owner='0'/>
        <file fileout='gzip compressed data' mode='100644' path='/usr/share/gtk-doc/html/pygtk/class-gtktextchildanchor.html' group='0' owner='0'/>
        <file fileout='gzip compressed data' mode='100644' path='/usr/share/gtk-doc/html/pygtk/class-gtkmenubar.html' group='0' owner='0'/>
        <file fileout='gzip compressed data' mode='100644' path='/usr/share/gtk-doc/html/pygtk/class-gtkprintoperationpreview.html' group='0' owner='0'/>
        <file fileout='gzip compressed data' mode='100644' path='/usr/share/gtk-doc/html/pygtk/class-gdkrectangle.html' group='0' owner='0'/>
        <file fileout='gzip compressed data' mode='100644' path='/usr/share/gtk-doc/html/pygtk/class-gdkcolormap.html' group='0' owner='0'/>
        <file fileout='gzip compressed data' mode='100644' path='/usr/share/gtk-doc/html/pygtk/class-gtktreeview.html' group='0' owner='0'/>
        <file fileout='gzip compressed data' mode='100644' path='/usr/share/gtk-doc/html/pygtk/class-gtkseparatormenuitem.html' group='0' owner='0'/>
        <file fileout='gzip compressed data' mode='100644' path='/usr/share/gtk-doc/html/pygtk/class-gtkcurve.html' group='0' owner='0'/>
        <file fileout='gzip compressed data' mode='100644' path='/usr/share/gtk-doc/html/pygtk/class-gtkspinbutton.html' group='0' owner='0'/>
        <file fileout='gzip compressed data' mode='100644' path='/usr/share/gtk-doc/html/pygtk/class-gtkcalendar.html' group='0' owner='0'/>
        <file mode='100644' path='/usr/share/gtk-doc/html/pygtk/class-gtkentrybuffer.html' group='0' owner='0'/>
        <file fileout='gzip compressed data' mode='100644' path='/usr/share/gtk-doc/html/pygtk/class-gtkcomboboxentry.html' group='0' owner='0'/>
        <file fileout='gzip compressed data' mode='100644' path='/usr/share/gtk-doc/html/pygtk/class-atkselection.html' group='0' owner='0'/>
        <file fileout='gzip compressed data' mode='100644' path='/usr/share/gtk-doc/html/pygtk/class-gtkhandlebox.html' group='0' owner='0'/>
        <file fileout='gzip compressed data' mode='100644' path='/usr/share/gtk-doc/html/pygtk/class-pangocairocairocontext.html' group='0' owner='0'/>
        <file fileout='gzip compressed data' mode='100644' path='/usr/share/gtk-doc/html/pygtk/class-gtklayout.html' group='0' owner='0'/>
        <file fileout='gzip compressed data' mode='100644' path='/usr/share/gtk-doc/html/pygtk/class-gdkcairocontext.html' group='0' owner='0'/>
        <file fileout='gzip compressed data' mode='100644' path='/usr/share/gtk-doc/html/pygtk/class-gtkseparatortoolitem.html' group='0' owner='0'/>
        <file fileout='gzip compressed data' mode='100644' path='/usr/share/gtk-doc/html/pygtk/pangocairo-functions.html' group='0' owner='0'/>
        <file fileout='gzip compressed data' mode='100644' path='/usr/share/gtk-doc/html/pygtk/class-gdkscreen.html' group='0' owner='0'/>
        <file fileout='gzip compressed data' mode='100644' path='/usr/share/gtk-doc/html/pygtk/pango-class-reference.html' group='0' owner='0'/>
        <file fileout='gzip compressed data' mode='100644' path='/usr/share/gtk-doc/html/pygtk/class-gtkcontainer.html' group='0' owner='0'/>
        <file fileout='gzip compressed data' mode='100644' path='/usr/share/gtk-doc/html/pygtk/class-gtkrecentaction.html' group='0' owner='0'/>
        <file fileout='gzip compressed data' mode='100644' path='/usr/share/gtk-doc/html/pygtk/class-gdkpixmap.html' group='0' owner='0'/>
        <file fileout='gzip compressed data' mode='100644' path='/usr/share/gtk-doc/html/pygtk/class-gtktreeviewcolumn.html' group='0' owner='0'/>
        <file fileout='gzip compressed data' mode='100644' path='/usr/share/gtk-doc/html/pygtk/class-gtkactiongroup.html' group='0' owner='0'/>
        <file fileout='gzip compressed data' mode='100644' path='/usr/share/gtk-doc/html/pygtk/class-gtkplug.html' group='0' owner='0'/>
        <file fileout='gzip compressed data' mode='100644' path='/usr/share/gtk-doc/html/pygtk/class-gtkhpaned.html' group='0' owner='0'/>
        <file fileout='gzip compressed data' mode='100644' path='/usr/share/gtk-doc/html/pygtk/class-gtkaboutdialog.html' group='0' owner='0'/>
        <file fileout='gzip compressed data' mode='100644' path='/usr/share/gtk-doc/html/pygtk/class-gtkscale.html' group='0' owner='0'/>
        <file fileout='gzip compressed data' mode='100644' path='/usr/share/gtk-doc/html/pygtk/pango-markup-language.html' group='0' owner='0'/>
        <file fileout='gzip compressed data' mode='100644' path='/usr/share/gtk-doc/html/pygtk/class-gtkfileselection.html' group='0' owner='0'/>
        <file fileout='gzip compressed data' mode='100644' path='/usr/share/gtk-doc/html/pygtk/class-gtkeditable.html' group='0' owner='0'/>
        <file fileout='gzip compressed data' mode='100644' path='/usr/share/gtk-doc/html/pygtk/class-gtkcolorselection.html' group='0' owner='0'/>
        <file fileout='gzip compressed data' mode='100644' path='/usr/share/gtk-doc/html/pygtk/class-hierarchy.html' group='0' owner='0'/>
        <file mode='100644' path='/usr/share/gtk-doc/html/pygtk/class-gtktoolitemgroup.html' group='0' owner='0'/>
        <file fileout='gzip compressed data' mode='100644' path='/usr/share/gtk-doc/html/pygtk/icons/stock_yes_20.png' group='0' owner='0'/>
        <file fileout='gzip compressed data' mode='100644' path='/usr/share/gtk-doc/html/pygtk/icons/stock_top_24.png' group='0' owner='0'/>
        <file fileout='gzip compressed data' mode='100644' path='/usr/share/gtk-doc/html/pygtk/icons/stock_media_play_rtl_24.png' group='0' owner='0'/>
        <file fileout='gzip compressed data' mode='100644' path='/usr/share/gtk-doc/html/pygtk/icons/stock_paste_24.png' group='0' owner='0'/>
        <file fileout='gzip compressed data' mode='100644' path='/usr/share/gtk-doc/html/pygtk/icons/stock_media_next_24.png' group='0' owner='0'/>
        <file fileout='gzip compressed data' mode='100644' path='/usr/share/gtk-doc/html/pygtk/icons/stock_media_pause_24.png' group='0' owner='0'/>
        <file fileout='gzip compressed data' mode='100644' path='/usr/share/gtk-doc/html/pygtk/icons/stock_new_24.png' group='0' owner='0'/>
        <file fileout='gzip compressed data' mode='100644' path='/usr/share/gtk-doc/html/pygtk/icons/stock_directory_24.png' group='0' owner='0'/>
        <file fileout='gzip compressed data' mode='100644' path='/usr/share/gtk-doc/html/pygtk/icons/stock_file_24.png' group='0' owner='0'/>
        <file fileout='gzip compressed data' mode='100644' path='/usr/share/gtk-doc/html/pygtk/icons/stock_color_picker_25.png' group='0' owner='0'/>
        <file fileout='gzip compressed data' mode='100644' path='/usr/share/gtk-doc/html/pygtk/icons/stock_disconnect_24.png' group='0' owner='0'/>
        <file fileout='gzip compressed data' mode='100644' path='/usr/share/gtk-doc/html/pygtk/icons/stock_apply_20.png' group='0' owner='0'/>
        <file fileout='gzip compressed data' mode='100644' path='/usr/share/gtk-doc/html/pygtk/icons/stock_zoom_out_24.png' group='0' owner='0'/>
        <file fileout='gzip compressed data' mode='100644' path='/usr/share/gtk-doc/html/pygtk/icons/stock_cancel_20.png' group='0' owner='0'/>
        <file fileout='gzip compressed data' mode='100644' path='/usr/share/gtk-doc/html/pygtk/icons/stock_index_24.png' group='0' owner='0'/>
        <file fileout='gzip compressed data' mode='100644' path='/usr/share/gtk-doc/html/pygtk/icons/stock_properties_24.png' group='0' owner='0'/>
        <file fileout='gzip compressed data' mode='100644' path='/usr/share/gtk-doc/html/pygtk/icons/stock_sort_ascending_24.png' group='0' owner='0'/>
        <file fileout='gzip compressed data' mode='100644' path='/usr/share/gtk-doc/html/pygtk/icons/stock_zoom_fit_24.png' group='0' owner='0'/>
        <file fileout='gzip compressed data' mode='100644' path='/usr/share/gtk-doc/html/pygtk/icons/stock_first_24.png' group='0' owner='0'/>
        <file fileout='gzip compressed data' mode='100644' path='/usr/share/gtk-doc/html/pygtk/icons/stock_harddisk_24.png' group='0' owner='0'/>
        <file fileout='gzip compressed data' mode='100644' path='/usr/share/gtk-doc/html/pygtk/icons/stock_print_error_24.png' group='0' owner='0'/>
        <file fileout='gzip compressed data' mode='100644' path='/usr/share/gtk-doc/html/pygtk/icons/stock_dialog_warning_48.png' group='0' owner='0'/>
        <file fileout='gzip compressed data' mode='100644' path='/usr/share/gtk-doc/html/pygtk/icons/stock_exec_24.png' group='0' owner='0'/>
        <file fileout='gzip compressed data' mode='100644' path='/usr/share/gtk-doc/html/pygtk/icons/stock_preferences_24.png' group='0' owner='0'/>
        <file fileout='gzip compressed data' mode='100644' path='/usr/share/gtk-doc/html/pygtk/icons/stock_revert_rtl_24.png' group='0' owner='0'/>
        <file fileout='gzip compressed data' mode='100644' path='/usr/share/gtk-doc/html/pygtk/icons/stock_dialog_question_48.png' group='0' owner='0'/>
        <file fileout='gzip compressed data' mode='100644' path='/usr/share/gtk-doc/html/pygtk/icons/stock_media_record_24.png' group='0' owner='0'/>
        <file fileout='gzip compressed data' mode='100644' path='/usr/share/gtk-doc/html/pygtk/icons/stock_text_underline_24.png' group='0' owner='0'/>
        <file fileout='gzip compressed data' mode='100644' path='/usr/share/gtk-doc/html/pygtk/icons/stock_dialog_authentication_48.png' group='0' owner='0'/>
        <file fileout='gzip compressed data' mode='100644' path='/usr/share/gtk-doc/html/pygtk/icons/stock_broken_image_24.png' group='0' owner='0'/>
        <file fileout='gzip compressed data' mode='100644' path='/usr/share/gtk-doc/html/pygtk/icons/stock_close_24.png' group='0' owner='0'/>
        <file fileout='gzip compressed data' mode='100644' path='/usr/share/gtk-doc/html/pygtk/icons/stock_save_as_24.png' group='0' owner='0'/>
        <file fileout='gzip compressed data' mode='100644' path='/usr/share/gtk-doc/html/pygtk/icons/stock_convert_24.png' group='0' owner='0'/>
        <file fileout='gzip compressed data' mode='100644' path='/usr/share/gtk-doc/html/pygtk/icons/stock_exit_24.png' group='0' owner='0'/>
        <file fileout='gzip compressed data' mode='100644' path='/usr/share/gtk-doc/html/pygtk/icons/stock_right_arrow_24.png' group='0' owner='0'/>
        <file fileout='gzip compressed data' mode='100644' path='/usr/share/gtk-doc/html/pygtk/icons/stock_undelete_24.png' group='0' owner='0'/>
        <file fileout='gzip compressed data' mode='100644' path='/usr/share/gtk-doc/html/pygtk/icons/stock_stop_24.png' group='0' owner='0'/>
        <file fileout='gzip compressed data' mode='100644' path='/usr/share/gtk-doc/html/pygtk/icons/stock_media_forward_24.png' group='0' owner='0'/>
        <file fileout='gzip compressed data' mode='100644' path='/usr/share/gtk-doc/html/pygtk/icons/stock_align_justify_24.png' group='0' owner='0'/>
        <file fileout='gzip compressed data' mode='100644' path='/usr/share/gtk-doc/html/pygtk/icons/stock_zoom_1_24.png' group='0' owner='0'/>
        <file fileout='gzip compressed data' mode='100644' path='/usr/share/gtk-doc/html/pygtk/icons/stock_no_20.png' group='0' owner='0'/>
        <file fileout='gzip compressed data' mode='100644' path='/usr/share/gtk-doc/html/pygtk/icons/stock_dialog_info_48.png' group='0' owner='0'/>
        <file fileout='gzip compressed data' mode='100644' path='/usr/share/gtk-doc/html/pygtk/icons/stock_text_strikethrough_24.png' group='0' owner='0'/>
        <file fileout='gzip compressed data' mode='100644' path='/usr/share/gtk-doc/html/pygtk/icons/stock_undelete_rtl_24.png' group='0' owner='0'/>
        <file fileout='gzip compressed data' mode='100644' path='/usr/share/gtk-doc/html/pygtk/icons/stock_dialog_error_48.png' group='0' owner='0'/>
        <file fileout='gzip compressed data' mode='100644' path='/usr/share/gtk-doc/html/pygtk/icons/stock_fullscreen_24.png' group='0' owner='0'/>
        <file fileout='gzip compressed data' mode='100644' path='/usr/share/gtk-doc/html/pygtk/icons/stock_undo_rtl_24.png' group='0' owner='0'/>
        <file fileout='gzip compressed data' mode='100644' path='/usr/share/gtk-doc/html/pygtk/icons/stock_bottom_24.png' group='0' owner='0'/>
        <file fileout='gzip compressed data' mode='100644' path='/usr/share/gtk-doc/html/pygtk/icons/stock_info_24.png' group='0' owner='0'/>
        <file fileout='gzip compressed data' mode='100644' path='/usr/share/gtk-doc/html/pygtk/icons/stock_dnd_multiple_32.png' group='0' owner='0'/>
        <file fileout='gzip compressed data' mode='100644' path='/usr/share/gtk-doc/html/pygtk/icons/stock_up_arrow_24.png' group='0' owner='0'/>
        <file fileout='gzip compressed data' mode='100644' path='/usr/share/gtk-doc/html/pygtk/icons/stock_home_24.png' group='0' owner='0'/>
        <file fileout='gzip compressed data' mode='100644' path='/usr/share/gtk-doc/html/pygtk/icons/stock_print_warning_24.png' group='0' owner='0'/>
        <file fileout='gzip compressed data' mode='100644' path='/usr/share/gtk-doc/html/pygtk/icons/stock_remove_24.png' group='0' owner='0'/>
        <file fileout='gzip compressed data' mode='100644' path='/usr/share/gtk-doc/html/pygtk/icons/stock_search_24.png' group='0' owner='0'/>
        <file fileout='gzip compressed data' mode='100644' path='/usr/share/gtk-doc/html/pygtk/icons/stock_left_arrow_24.png' group='0' owner='0'/>
        <file fileout='gzip compressed data' mode='100644' path='/usr/share/gtk-doc/html/pygtk/icons/stock_text_unindent_24.png' group='0' owner='0'/>
        <file fileout='gzip compressed data' mode='100644' path='/usr/share/gtk-doc/html/pygtk/icons/stock_sort_descending_24.png' group='0' owner='0'/>
        <file fileout='gzip compressed data' mode='100644' path='/usr/share/gtk-doc/html/pygtk/icons/stock_down_arrow_24.png' group='0' owner='0'/>
        <file fileout='gzip compressed data' mode='100644' path='/usr/share/gtk-doc/html/pygtk/icons/stock_text_bold_24.png' group='0' owner='0'/>
        <file fileout='gzip compressed data' mode='100644' path='/usr/share/gtk-doc/html/pygtk/icons/stock_align_right_24.png' group='0' owner='0'/>
        <file fileout='gzip compressed data' mode='100644' path='/usr/share/gtk-doc/html/pygtk/icons/stock_search_replace_24.png' group='0' owner='0'/>
        <file fileout='gzip compressed data' mode='100644' path='/usr/share/gtk-doc/html/pygtk/icons/stock_text_indent_24.png' group='0' owner='0'/>
        <file fileout='gzip compressed data' mode='100644' path='/usr/share/gtk-doc/html/pygtk/icons/stock_colorselector_24.png' group='0' owner='0'/>
        <file fileout='gzip compressed data' mode='100644' path='/usr/share/gtk-doc/html/pygtk/icons/stock_edit_24.png' group='0' owner='0'/>
        <file fileout='gzip compressed data' mode='100644' path='/usr/share/gtk-doc/html/pygtk/icons/stock_print_paused_24.png' group='0' owner='0'/>
        <file fileout='gzip compressed data' mode='100644' path='/usr/share/gtk-doc/html/pygtk/icons/stock_clear_24.png' group='0' owner='0'/>
        <file fileout='gzip compressed data' mode='100644' path='/usr/share/gtk-doc/html/pygtk/icons/stock_spellcheck_24.png' group='0' owner='0'/>
        <file fileout='gzip compressed data' mode='100644' path='/usr/share/gtk-doc/html/pygtk/icons/stock_cut_24.png' group='0' owner='0'/>
        <file fileout='gzip compressed data' mode='100644' path='/usr/share/gtk-doc/html/pygtk/icons/stock_media_rewind_24.png' group='0' owner='0'/>
        <file fileout='gzip compressed data' mode='100644' path='/usr/share/gtk-doc/html/pygtk/icons/stock_help_24.png' group='0' owner='0'/>
        <file fileout='gzip compressed data' mode='100644' path='/usr/share/gtk-doc/html/pygtk/icons/stock_zoom_in_24.png' group='0' owner='0'/>
        <file fileout='gzip compressed data' mode='100644' path='/usr/share/gtk-doc/html/pygtk/icons/stock_jump_to_24.png' group='0' owner='0'/>
        <file fileout='gzip compressed data' mode='100644' path='/usr/share/gtk-doc/html/pygtk/icons/stock_media_stop_24.png' group='0' owner='0'/>
        <file fileout='gzip compressed data' mode='100644' path='/usr/share/gtk-doc/html/pygtk/icons/stock_revert_24.png' group='0' owner='0'/>
        <file fileout='gzip compressed data' mode='100644' path='/usr/share/gtk-doc/html/pygtk/icons/stock_print_report_24.png' group='0' owner='0'/>
        <file fileout='gzip compressed data' mode='100644' path='/usr/share/gtk-doc/html/pygtk/icons/stock_media_play_24.png' group='0' owner='0'/>
        <file fileout='gzip compressed data' mode='100644' path='/usr/share/gtk-doc/html/pygtk/icons/stock_align_center_24.png' group='0' owner='0'/>
        <file fileout='gzip compressed data' mode='100644' path='/usr/share/gtk-doc/html/pygtk/icons/stock_media_previous_24.png' group='0' owner='0'/>
        <file fileout='gzip compressed data' mode='100644' path='/usr/share/gtk-doc/html/pygtk/icons/stock_redo_rtl_24.png' group='0' owner='0'/>
        <file fileout='gzip compressed data' mode='100644' path='/usr/share/gtk-doc/html/pygtk/icons/stock_undo_24.png' group='0' owner='0'/>
        <file fileout='gzip compressed data' mode='100644' path='/usr/share/gtk-doc/html/pygtk/icons/stock_copy_24.png' group='0' owner='0'/>
        <file fileout='gzip compressed data' mode='100644' path='/usr/share/gtk-doc/html/pygtk/icons/stock_leave_fullscreen_24.png' group='0' owner='0'/>
        <file fileout='gzip compressed data' mode='100644' path='/usr/share/gtk-doc/html/pygtk/icons/stock_dnd_32.png' group='0' owner='0'/>
        <file fileout='gzip compressed data' mode='100644' path='/usr/share/gtk-doc/html/pygtk/icons/stock_save_24.png' group='0' owner='0'/>
        <file fileout='gzip compressed data' mode='100644' path='/usr/share/gtk-doc/html/pygtk/icons/stock_print_preview_24.png' group='0' owner='0'/>
        <file fileout='gzip compressed data' mode='100644' path='/usr/share/gtk-doc/html/pygtk/icons/stock_redo_24.png' group='0' owner='0'/>
        <file fileout='gzip compressed data' mode='100644' path='/usr/share/gtk-doc/html/pygtk/icons/stock_align_left_24.png' group='0' owner='0'/>
        <file fileout='gzip compressed data' mode='100644' path='/usr/share/gtk-doc/html/pygtk/icons/stock_text_italic_24.png' group='0' owner='0'/>
        <file fileout='gzip compressed data' mode='100644' path='/usr/share/gtk-doc/html/pygtk/icons/stock_connect_24.png' group='0' owner='0'/>
        <file fileout='gzip compressed data' mode='100644' path='/usr/share/gtk-doc/html/pygtk/icons/stock_page_setup_24.png' group='0' owner='0'/>
        <file fileout='gzip compressed data' mode='100644' path='/usr/share/gtk-doc/html/pygtk/icons/stock_open_24.png' group='0' owner='0'/>
        <file fileout='gzip compressed data' mode='100644' path='/usr/share/gtk-doc/html/pygtk/icons/stock_about_24.png' group='0' owner='0'/>
        <file fileout='gzip compressed data' mode='100644' path='/usr/share/gtk-doc/html/pygtk/icons/stock_print_24.png' group='0' owner='0'/>
        <file fileout='gzip compressed data' mode='100644' path='/usr/share/gtk-doc/html/pygtk/icons/stock_refresh_24.png' group='0' owner='0'/>
        <file fileout='gzip compressed data' mode='100644' path='/usr/share/gtk-doc/html/pygtk/icons/stock_last_24.png' group='0' owner='0'/>
        <file fileout='gzip compressed data' mode='100644' path='/usr/share/gtk-doc/html/pygtk/icons/stock_network_24.png' group='0' owner='0'/>
        <file fileout='gzip compressed data' mode='100644' path='/usr/share/gtk-doc/html/pygtk/icons/stock_trash_24.png' group='0' owner='0'/>
        <file fileout='gzip compressed data' mode='100644' path='/usr/share/gtk-doc/html/pygtk/icons/stock_ok_20.png' group='0' owner='0'/>
        <file fileout='gzip compressed data' mode='100644' path='/usr/share/gtk-doc/html/pygtk/icons/stock_jump_to_rtl_24.png' group='0' owner='0'/>
        <file fileout='gzip compressed data' mode='100644' path='/usr/share/gtk-doc/html/pygtk/icons/stock_font_24.png' group='0' owner='0'/>
        <file fileout='gzip compressed data' mode='100644' path='/usr/share/gtk-doc/html/pygtk/icons/stock_add_24.png' group='0' owner='0'/>
        <file fileout='gzip compressed data' mode='100644' path='/usr/share/gtk-doc/html/pygtk/icons/stock_cdrom_24.png' group='0' owner='0'/>
        <file fileout='gzip compressed data' mode='100644' path='/usr/share/gtk-doc/html/pygtk/class-gdkimage.html' group='0' owner='0'/>
        <file fileout='gzip compressed data' mode='100644' path='/usr/share/gtk-doc/html/pygtk/class-gdkcursor.html' group='0' owner='0'/>
        <file fileout='gzip compressed data' mode='100644' path='/usr/share/gtk-doc/html/pygtk/class-gtktreemodel.html' group='0' owner='0'/>
        <file fileout='gzip compressed data' mode='100644' path='/usr/share/gtk-doc/html/pygtk/class-gtkfilechooser.html' group='0' owner='0'/>
        <file fileout='gzip compressed data' mode='100644' path='/usr/share/gtk-doc/html/pygtk/class-gtkbuildable.html' group='0' owner='0'/>
        <file fileout='gzip compressed data' mode='100644' path='/usr/share/gtk-doc/html/pygtk/class-gtkcellrendereraccel.html' group='0' owner='0'/>
        <file fileout='gzip compressed data' mode='100644' path='/usr/share/gtk-doc/html/pygtk/class-gtkobject.html' group='0' owner='0'/>
        <file fileout='gzip compressed data' mode='100644' path='/usr/share/gtk-doc/html/pygtk/class-gtkcheckmenuitem.html' group='0' owner='0'/>
        <file fileout='gzip compressed data' mode='100644' path='/usr/share/gtk-doc/html/pygtk/class-gtkrecentinfo.html' group='0' owner='0'/>
        <file fileout='gzip compressed data' mode='100644' path='/usr/share/gtk-doc/html/pygtk/class-pangolayoutiter.html' group='0' owner='0'/>
        <file fileout='gzip compressed data' mode='100644' path='/usr/share/gtk-doc/html/pygtk/class-gtktreedragdest.html' group='0' owner='0'/>
        <file fileout='gzip compressed data' mode='100644' path='/usr/share/gtk-doc/html/pygtk/class-gtkcellrendererprogress.html' group='0' owner='0'/>
        <file fileout='gzip compressed data' mode='100644' path='/usr/share/gtk-doc/html/pygtk/class-gtkvscale.html' group='0' owner='0'/>
        <file fileout='gzip compressed data' mode='100644' path='/usr/share/gtk-doc/html/pygtk/class-gtkwidget.html' group='0' owner='0'/>
        <file fileout='gzip compressed data' mode='100644' path='/usr/share/gtk-doc/html/pygtk/class-gdkkeymap.html' group='0' owner='0'/>
        <file fileout='gzip compressed data' mode='100644' path='/usr/share/gtk-doc/html/pygtk/class-gdkregion.html' group='0' owner='0'/>
        <file fileout='gzip compressed data' mode='100644' path='/usr/share/gtk-doc/html/pygtk/class-gtkicontheme.html' group='0' owner='0'/>
        <file fileout='gzip compressed data' mode='100644' path='/usr/share/gtk-doc/html/pygtk/class-gtkgammacurve.html' group='0' owner='0'/>
        <file fileout='gzip compressed data' mode='100644' path='/usr/share/gtk-doc/html/pygtk/class-gtktexttagtable.html' group='0' owner='0'/>
        <file fileout='gzip compressed data' mode='100644' path='/usr/share/gtk-doc/html/pygtk/class-gtktreeiter.html' group='0' owner='0'/>
        <file fileout='gzip compressed data' mode='100644' path='/usr/share/gtk-doc/html/pygtk/class-gtktextiter.html' group='0' owner='0'/>
        <file fileout='gzip compressed data' mode='100644' path='/usr/share/gtk-doc/html/pygtk/class-gtkbuttonbox.html' group='0' owner='0'/>
        <file fileout='gzip compressed data' mode='100644' path='/usr/share/gtk-doc/html/pygtk/class-gtkbox.html' group='0' owner='0'/>
        <file fileout='gzip compressed data' mode='100644' path='/usr/share/gtk-doc/html/pygtk/class-gdkpixbufanimation.html' group='0' owner='0'/>
        <file fileout='gzip compressed data' mode='100644' path='/usr/share/gtk-doc/html/pygtk/class-gdkevent.html' group='0' owner='0'/>
        <file fileout='gzip compressed data' mode='100644' path='/usr/share/gtk-doc/html/pygtk/class-gtktearoffmenuitem.html' group='0' owner='0'/>
        <file fileout='gzip compressed data' mode='100644' path='/usr/share/gtk-doc/html/pygtk/class-gtkcellrenderer.html' group='0' owner='0'/>
        <file fileout='gzip compressed data' mode='100644' path='/usr/share/gtk-doc/html/pygtk/class-gtktoolbar.html' group='0' owner='0'/>
        <file fileout='gzip compressed data' mode='100644' path='/usr/share/gtk-doc/html/pygtk/glade-class-reference.html' group='0' owner='0'/>
        <file fileout='gzip compressed data' mode='100644' path='/usr/share/gtk-doc/html/pygtk/class-gtkhbox.html' group='0' owner='0'/>
        <file fileout='gzip compressed data' mode='100644' path='/usr/share/gtk-doc/html/pygtk/class-gtklabel.html' group='0' owner='0'/>
        <file fileout='gzip compressed data' mode='100644' path='/usr/share/gtk-doc/html/pygtk/class-gdkwindow.html' group='0' owner='0'/>
        <file fileout='gzip compressed data' mode='100644' path='/usr/share/gtk-doc/html/pygtk/class-gtkbutton.html' group='0' owner='0'/>
        <file fileout='gzip compressed data' mode='100644' path='/usr/share/gtk-doc/html/pygtk/class-gtkmenutoolbutton.html' group='0' owner='0'/>
        <file fileout='gzip compressed data' mode='100644' path='/usr/share/gtk-doc/html/pygtk/class-gtkcellrendererpixbuf.html' group='0' owner='0'/>
        <file fileout='gzip compressed data' mode='100644' path='/usr/share/gtk-doc/html/pygtk/class-atknoopobject.html' group='0' owner='0'/>
        <file fileout='gzip compressed data' mode='100644' path='/usr/share/gtk-doc/html/pygtk/class-gtktoggleaction.html' group='0' owner='0'/>
        <file fileout='gzip compressed data' mode='100644' path='/usr/share/gtk-doc/html/pygtk/class-atkimage.html' group='0' owner='0'/>
        <file fileout='gzip compressed data' mode='100644' path='/usr/share/gtk-doc/html/pygtk/class-gtkcelleditable.html' group='0' owner='0'/>
        <file fileout='gzip compressed data' mode='100644' path='/usr/share/gtk-doc/html/pygtk/class-pygtkgenericcellrenderer.html' group='0' owner='0'/>
        <file fileout='gzip compressed data' mode='100644' path='/usr/share/gtk-doc/html/pygtk/class-gtktoolbutton.html' group='0' owner='0'/>
        <file fileout='gzip compressed data' mode='100644' path='/usr/share/gtk-doc/html/pygtk/gdk-class-reference.html' group='0' owner='0'/>
        <file fileout='gzip compressed data' mode='100644' path='/usr/share/gtk-doc/html/pygtk/class-atkrectangle.html' group='0' owner='0'/>
        <file fileout='gzip compressed data' mode='100644' path='/usr/share/gtk-doc/html/pygtk/class-atknoopobjectfactory.html' group='0' owner='0'/>
        <file fileout='gzip compressed data' mode='100644' path='/usr/share/gtk-doc/html/pygtk/class-gtkbin.html' group='0' owner='0'/>
        <file fileout='gzip compressed data' mode='100644' path='/usr/share/gtk-doc/html/pygtk/class-gtkmessagedialog.html' group='0' owner='0'/>
        <file fileout='gzip compressed data' mode='100644' path='/usr/share/gtk-doc/html/pygtk/class-gtktoggletoolbutton.html' group='0' owner='0'/>
        <file fileout='gzip compressed data' mode='100644' path='/usr/share/gtk-doc/html/pygtk/class-gtkhseparator.html' group='0' owner='0'/>
        <file fileout='gzip compressed data' mode='100644' path='/usr/share/gtk-doc/html/pygtk/class-gtkrecentfilter.html' group='0' owner='0'/>
        <file fileout='gzip compressed data' mode='100644' path='/usr/share/gtk-doc/html/pygtk/class-gtkstatusicon.html' group='0' owner='0'/>
        <file fileout='gzip compressed data' mode='100644' path='/usr/share/gtk-doc/html/pygtk/class-gtkentry.html' group='0' owner='0'/>
        <file fileout='gzip compressed data' mode='100644' path='/usr/share/gtk-doc/html/pygtk/class-atkstreamablecontent.html' group='0' owner='0'/>
        <file fileout='gzip compressed data' mode='100644' path='/usr/share/gtk-doc/html/pygtk/class-gtksizegroup.html' group='0' owner='0'/>
        <file fileout='gzip compressed data' mode='100644' path='/usr/share/gtk-doc/html/pygtk/class-pangotabarray.html' group='0' owner='0'/>
        <file fileout='gzip compressed data' mode='100644' path='/usr/share/gtk-doc/html/pygtk/class-gtkvbuttonbox.html' group='0' owner='0'/>
        <file fileout='gzip compressed data' mode='100644' path='/usr/share/gtk-doc/html/pygtk/pango-functions.html' group='0' owner='0'/>
        <file fileout='gzip compressed data' mode='100644' path='/usr/share/gtk-doc/html/pygtk/class-pygtktreemodelrowiter.html' group='0' owner='0'/>
        <file fileout='gzip compressed data' mode='100644' path='/usr/share/gtk-doc/html/pygtk/gtk-class-reference.html' group='0' owner='0'/>
        <file fileout='gzip compressed data' mode='100644' path='/usr/share/gtk-doc/html/pygtk/class-gtkimmulticontext.html' group='0' owner='0'/>
        <file fileout='gzip compressed data' mode='100644' path='/usr/share/gtk-doc/html/pygtk/class-gtkstyle.html' group='0' owner='0'/>
        <file fileout='gzip compressed data' mode='100644' path='/usr/share/gtk-doc/html/pygtk/class-pangofontmetrics.html' group='0' owner='0'/>
        <file fileout='gzip compressed data' mode='100644' path='/usr/share/gtk-doc/html/pygtk/class-gtkrecentchoosermenu.html' group='0' owner='0'/>
        <file fileout='gzip compressed data' mode='100644' path='/usr/share/gtk-doc/html/pygtk/class-gtkpagesetup.html' group='0' owner='0'/>
        <file fileout='gzip compressed data' mode='100644' path='/usr/share/gtk-doc/html/pygtk/pangocairo-class-reference.html' group='0' owner='0'/>
        <file fileout='gzip compressed data' mode='100644' path='/usr/share/gtk-doc/html/pygtk/gtk-stock-items.html' group='0' owner='0'/>
        <file fileout='gzip compressed data' mode='100644' path='/usr/share/gtk-doc/html/pygtk/class-gtkexpander.html' group='0' owner='0'/>
        <file fileout='gzip compressed data' mode='100644' path='/usr/share/gtk-doc/html/pygtk/class-atkaction.html' group='0' owner='0'/>
        <file fileout='gzip compressed data' mode='100644' path='/usr/share/gtk-doc/html/pygtk/gdk-constants.html' group='0' owner='0'/>
        <file fileout='gzip compressed data' mode='100644' path='/usr/share/gtk-doc/html/pygtk/class-gladexml.html' group='0' owner='0'/>
        <file fileout='gzip compressed data' mode='100644' path='/usr/share/gtk-doc/html/pygtk/class-gtkhruler.html' group='0' owner='0'/>
        <file fileout='gzip compressed data' mode='100644' path='/usr/share/gtk-doc/html/pygtk/class-atkstateset.html' group='0' owner='0'/>
        <file fileout='gzip compressed data' mode='100644' path='/usr/share/gtk-doc/html/pygtk/class-gtkcolorselectiondialog.html' group='0' owner='0'/>
        <file fileout='gzip compressed data' mode='100644' path='/usr/share/gtk-doc/html/pygtk/class-gdkcolor.html' group='0' owner='0'/>
        <file fileout='gzip compressed data' mode='100644' path='/usr/share/gtk-doc/html/pygtk/class-gtkactivatable.html' group='0' owner='0'/>
        <file fileout='gzip compressed data' mode='100644' path='/usr/share/gtk-doc/html/pygtk/class-gdkpixbufloader.html' group='0' owner='0'/>
        <file fileout='gzip compressed data' mode='100644' path='/usr/share/gtk-doc/html/pygtk/class-gtkaction.html' group='0' owner='0'/>
        <file fileout='gzip compressed data' mode='100644' path='/usr/share/gtk-doc/html/pygtk/class-atkrelation.html' group='0' owner='0'/>
        <file fileout='gzip compressed data' mode='100644' path='/usr/share/gtk-doc/html/pygtk/class-gtksocket.html' group='0' owner='0'/>
        <file fileout='gzip compressed data' mode='100644' path='/usr/share/gtk-doc/html/pygtk/class-gtkvseparator.html' group='0' owner='0'/>
        <file fileout='gzip compressed data' mode='100644' path='/usr/share/gtk-doc/html/pygtk/class-pangocolor.html' group='0' owner='0'/>
        <file fileout='gzip compressed data' mode='100644' path='/usr/share/gtk-doc/html/pygtk/class-gtkprinter.html' group='0' owner='0'/>
        <file fileout='gzip compressed data' mode='100644' path='/usr/share/gtk-doc/html/pygtk/class-gtkvruler.html' group='0' owner='0'/>
        <file fileout='gzip compressed data' mode='100644' path='/usr/share/gtk-doc/html/pygtk/unixprint-functions.html' group='0' owner='0'/>
        <file fileout='gzip compressed data' mode='100644' path='/usr/share/gtk-doc/html/pygtk/class-gtktreerowreference.html' group='0' owner='0'/>
        <file fileout='gzip compressed data' mode='100644' path='/usr/share/gtk-doc/html/pygtk/class-gtkentrycompletion.html' group='0' owner='0'/>
        <file fileout='gzip compressed data' mode='100644' path='/usr/share/gtk-doc/html/pygtk/class-gtklinkbutton.html' group='0' owner='0'/>
        <file fileout='gzip compressed data' mode='100644' path='/usr/share/gtk-doc/html/pygtk/class-atkobject.html' group='0' owner='0'/>
        <file fileout='gzip compressed data' mode='100644' path='/usr/share/gtk-doc/html/pygtk/class-gdkdevice.html' group='0' owner='0'/>
        <file fileout='gzip compressed data' mode='100644' path='/usr/share/gtk-doc/html/pygtk/class-pangolanguage.html' group='0' owner='0'/>
        <file fileout='gzip compressed data' mode='100644' path='/usr/share/gtk-doc/html/pygtk/class-gtkrequisition.html' group='0' owner='0'/>
        <file mode='100644' path='/usr/share/gtk-doc/html/pygtk/class-gtktoolpalette.html' group='0' owner='0'/>
        <file fileout='gzip compressed data' mode='100644' path='/usr/share/gtk-doc/html/pygtk/class-gtkarrow.html' group='0' owner='0'/>
        <file fileout='gzip compressed data' mode='100644' path='/usr/share/gtk-doc/html/pygtk/class-gtkprintjob.html' group='0' owner='0'/>
        <file fileout='gzip compressed data' mode='100644' path='/usr/share/gtk-doc/html/pygtk/class-gtkframe.html' group='0' owner='0'/>
        <file fileout='gzip compressed data' mode='100644' path='/usr/share/gtk-doc/html/pygtk/class-gtkcolorbutton.html' group='0' owner='0'/>
        <file mode='100644' path='/usr/share/gtk-doc/html/pygtk/class-gtkspinner.html' group='0' owner='0'/>
        <file fileout='gzip compressed data' mode='100644' path='/usr/share/gtk-doc/html/pygtk/class-gtkcellrenderertoggle.html' group='0' owner='0'/>
        <file fileout='gzip compressed data' mode='100644' path='/usr/share/gtk-doc/html/pygtk/class-pangoattrlist.html' group='0' owner='0'/>
        <file fileout='gzip compressed data' mode='100644' path='/usr/share/gtk-doc/html/pygtk/class-gtkpapersize.html' group='0' owner='0'/>
        <file fileout='gzip compressed data' mode='100644' path='/usr/share/gtk-doc/html/pygtk/class-gtktooltip.html' group='0' owner='0'/>
        <file fileout='gzip compressed data' mode='100644' path='/usr/share/gtk-doc/html/pygtk/class-gtktextattributes.html' group='0' owner='0'/>
        <file fileout='gzip compressed data' mode='100644' path='/usr/share/gtk-doc/html/pygtk/class-pangocontext.html' group='0' owner='0'/>
        <file fileout='gzip compressed data' mode='100644' path='/usr/share/gtk-doc/html/pygtk/class-gtkradiotoolbutton.html' group='0' owner='0'/>
        <file fileout='gzip compressed data' mode='100644' path='/usr/share/gtk-doc/html/pygtk/class-gtkitemfactory.html' group='0' owner='0'/>
        <file fileout='gzip compressed data' mode='100644' path='/usr/share/gtk-doc/html/pygtk/images/layout-tbrl.png' group='0' owner='0'/>
        <file fileout='gzip compressed data' mode='100644' path='/usr/share/gtk-doc/html/pygtk/images/layout-btlr.png' group='0' owner='0'/>
        <file fileout='gzip compressed data' mode='100644' path='/usr/share/gtk-doc/html/pygtk/images/layout-btrl.png' group='0' owner='0'/>
        <file fileout='gzip compressed data' mode='100644' path='/usr/share/gtk-doc/html/pygtk/images/layout-lrbt.png' group='0' owner='0'/>
        <file fileout='gzip compressed data' mode='100644' path='/usr/share/gtk-doc/html/pygtk/images/layout-tblr.png' group='0' owner='0'/>
        <file fileout='gzip compressed data' mode='100644' path='/usr/share/gtk-doc/html/pygtk/images/layout-rlbt.png' group='0' owner='0'/>
        <file fileout='gzip compressed data' mode='100644' path='/usr/share/gtk-doc/html/pygtk/images/layout-rltb.png' group='0' owner='0'/>
        <file fileout='gzip compressed data' mode='100644' path='/usr/share/gtk-doc/html/pygtk/images/layout-lrtb.png' group='0' owner='0'/>
        <file fileout='gzip compressed data' mode='100644' path='/usr/share/gtk-doc/html/pygtk/class-pangofont.html' group='0' owner='0'/>
    </subpackage>
    <subpackage name='config'>
        <file mode='100644' path='/etc/ld.so.cache' group='0' owner='0'/>
    </subpackage>
    <subpackage name='devel'>
        <file fileout='ASCII text' mode='100644' path='/usr/lib/pkgconfig/pygtk-2.0.pc' group='0' owner='0'/>
        <file fileout='libtool library file, ' mode='100755' path='/usr/lib/python2.7/site-packages/gtk-2.0/atk.la' group='0' owner='0'/>
        <file fileout='libtool library file, ' mode='100755' path='/usr/lib/python2.7/site-packages/gtk-2.0/gtk/glade.la' group='0' owner='0'/>
        <file fileout='libtool library file, ' mode='100755' path='/usr/lib/python2.7/site-packages/gtk-2.0/gtk/_gtk.la' group='0' owner='0'/>
        <file fileout='libtool library file, ' mode='100755' path='/usr/lib/python2.7/site-packages/gtk-2.0/pangocairo.la' group='0' owner='0'/>
        <file fileout='libtool library file, ' mode='100755' path='/usr/lib/python2.7/site-packages/gtk-2.0/pango.la' group='0' owner='0'/>
        <file fileout='libtool library file, ' mode='100755' path='/usr/lib/python2.7/site-packages/gtk-2.0/gtkunixprint.la' group='0' owner='0'/>
        <file fileout='ASCII C program text' mode='100644' path='/usr/include/pygtk-2.0/pygtk/pygtk.h' group='0' owner='0'/>
    </subpackage>
    <subpackage name='localization'/>
    <subpackage name='tzdata'/>
    <subpackage name='uncategorized'>
        <file fileout='python 2.7 byte-compiled' mode='100644' path='/usr/lib/pygtk/2.0/pygtk-demo.pyc' group='0' owner='0'/>
        <file fileout='python 2.7 byte-compiled' mode='100644' path='/usr/lib/pygtk/2.0/pygtk-demo.pyo' group='0' owner='0'/>
        <file fileout='python 2.7 byte-compiled' mode='100644' path='/usr/lib/pygtk/2.0/demos/expander.pyc' group='0' owner='0'/>
        <file fileout='ASCII text' mode='100644' path='/usr/lib/pygtk/2.0/demos/dndpixmap.py' group='0' owner='0'/>
        <file fileout='python 2.7 byte-compiled' mode='100644' path='/usr/lib/pygtk/2.0/demos/hypertext.pyo' group='0' owner='0'/>
        <file fileout='a python script, ASCII text executable' mode='100644' path='/usr/lib/pygtk/2.0/demos/pixbufs.py' group='0' owner='0'/>
        <file fileout='a python script, ASCII text executable' mode='100644' path='/usr/lib/pygtk/2.0/demos/tree_store.py' group='0' owner='0'/>
        <file fileout='python 2.7 byte-compiled' mode='100644' path='/usr/lib/pygtk/2.0/demos/tooltip.pyc' group='0' owner='0'/>
        <file fileout='python 2.7 byte-compiled' mode='100644' path='/usr/lib/pygtk/2.0/demos/treemodel.pyc' group='0' owner='0'/>
        <file fileout='python 2.7 byte-compiled' mode='100644' path='/usr/lib/pygtk/2.0/demos/statusicon.pyc' group='0' owner='0'/>
        <file fileout='python 2.7 byte-compiled' mode='100644' path='/usr/lib/pygtk/2.0/demos/menu.pyo' group='0' owner='0'/>
        <file fileout='python 2.7 byte-compiled' mode='100644' path='/usr/lib/pygtk/2.0/demos/__init__.pyc' group='0' owner='0'/>
        <file fileout='a python script, ASCII text executable' mode='100644' path='/usr/lib/pygtk/2.0/demos/images.py' group='0' owner='0'/>
        <file fileout='python 2.7 byte-compiled' mode='100644' path='/usr/lib/pygtk/2.0/demos/statusicon.pyo' group='0' owner='0'/>
        <file fileout='a python script, ASCII text executable' mode='100644' path='/usr/lib/pygtk/2.0/demos/buttonbox.py' group='0' owner='0'/>
        <file fileout='python 2.7 byte-compiled' mode='100644' path='/usr/lib/pygtk/2.0/demos/panes.pyo' group='0' owner='0'/>
        <file fileout='python 2.7 byte-compiled' mode='100644' path='/usr/lib/pygtk/2.0/demos/print_editor.pyc' group='0' owner='0'/>
        <file fileout='python 2.7 byte-compiled' mode='100644' path='/usr/lib/pygtk/2.0/demos/appwindow.pyc' group='0' owner='0'/>
        <file fileout='a python script, ASCII text executable' mode='100644' path='/usr/lib/pygtk/2.0/demos/panes.py' group='0' owner='0'/>
        <file fileout='python 2.7 byte-compiled' mode='100644' path='/usr/lib/pygtk/2.0/demos/editable_cells.pyc' group='0' owner='0'/>
        <file fileout='python 2.7 byte-compiled' mode='100644' path='/usr/lib/pygtk/2.0/demos/editable_cells.pyo' group='0' owner='0'/>
        <file fileout='python 2.7 byte-compiled' mode='100644' path='/usr/lib/pygtk/2.0/demos/changedisplay.pyc' group='0' owner='0'/>
        <file fileout='python 2.7 byte-compiled' mode='100644' path='/usr/lib/pygtk/2.0/demos/entry_completion.pyo' group='0' owner='0'/>
        <file fileout='a python script, ASCII text executable' mode='100644' path='/usr/lib/pygtk/2.0/demos/changedisplay.py' group='0' owner='0'/>
        <file fileout='python 2.7 byte-compiled' mode='100644' path='/usr/lib/pygtk/2.0/demos/tree_store.pyo' group='0' owner='0'/>
        <file fileout='python 2.7 byte-compiled' mode='100644' path='/usr/lib/pygtk/2.0/demos/list_store.pyc' group='0' owner='0'/>
        <file fileout='python 2.7 byte-compiled' mode='100644' path='/usr/lib/pygtk/2.0/demos/menu.pyc' group='0' owner='0'/>
        <file fileout='python 2.7 byte-compiled' mode='100644' path='/usr/lib/pygtk/2.0/demos/sizegroup.pyo' group='0' owner='0'/>
        <file fileout='python 2.7 byte-compiled' mode='100644' path='/usr/lib/pygtk/2.0/demos/textview.pyo' group='0' owner='0'/>
        <file fileout='a python script, ASCII text executable' mode='100644' path='/usr/lib/pygtk/2.0/demos/hypertext.py' group='0' owner='0'/>
        <file fileout='python 2.7 byte-compiled' mode='100644' path='/usr/lib/pygtk/2.0/demos/textscroll.pyc' group='0' owner='0'/>
        <file fileout='a python script, ASCII text executable' mode='100644' path='/usr/lib/pygtk/2.0/demos/expander.py' group='0' owner='0'/>
        <file fileout='a python script, ASCII text executable' mode='100644' path='/usr/lib/pygtk/2.0/demos/colorsel.py' group='0' owner='0'/>
        <file fileout='python 2.7 byte-compiled' mode='100644' path='/usr/lib/pygtk/2.0/demos/changedisplay.pyo' group='0' owner='0'/>
        <file fileout='a python script, ASCII text executable' mode='100644' path='/usr/lib/pygtk/2.0/demos/tooltip.py' group='0' owner='0'/>
        <file fileout='python 2.7 byte-compiled' mode='100644' path='/usr/lib/pygtk/2.0/demos/panes.pyc' group='0' owner='0'/>
        <file fileout='a python script, ASCII text executable' mode='100644' path='/usr/lib/pygtk/2.0/demos/treemodel.py' group='0' owner='0'/>
        <file fileout='python 2.7 byte-compiled' mode='100644' path='/usr/lib/pygtk/2.0/demos/buttonbox.pyo' group='0' owner='0'/>
        <file fileout='python 2.7 byte-compiled' mode='100644' path='/usr/lib/pygtk/2.0/demos/ui_manager.pyc' group='0' owner='0'/>
        <file fileout='a python script, ASCII text executable' mode='100644' path='/usr/lib/pygtk/2.0/demos/textview.py' group='0' owner='0'/>
        <file fileout='python 2.7 byte-compiled' mode='100644' path='/usr/lib/pygtk/2.0/demos/appwindow.pyo' group='0' owner='0'/>
        <file fileout='python 2.7 byte-compiled' mode='100644' path='/usr/lib/pygtk/2.0/demos/dialogs.pyo' group='0' owner='0'/>
        <file fileout='a python script, ASCII text executable' mode='100644' path='/usr/lib/pygtk/2.0/demos/editable_cells.py' group='0' owner='0'/>
        <file fileout='a python script, ASCII text executable' mode='100644' path='/usr/lib/pygtk/2.0/demos/entry_completion.py' group='0' owner='0'/>
        <file fileout='python 2.7 byte-compiled' mode='100644' path='/usr/lib/pygtk/2.0/demos/tree_store.pyc' group='0' owner='0'/>
        <file fileout='a python script, ASCII text executable' mode='100644' path='/usr/lib/pygtk/2.0/demos/textscroll.py' group='0' owner='0'/>
        <file fileout='python 2.7 byte-compiled' mode='100644' path='/usr/lib/pygtk/2.0/demos/hypertext.pyc' group='0' owner='0'/>
        <file mode='100644' path='/usr/lib/pygtk/2.0/demos/infobar.pyo' group='0' owner='0'/>
        <file fileout='python 2.7 byte-compiled' mode='100644' path='/usr/lib/pygtk/2.0/demos/sizegroup.pyc' group='0' owner='0'/>
        <file fileout='python 2.7 byte-compiled' mode='100644' path='/usr/lib/pygtk/2.0/demos/textview.pyc' group='0' owner='0'/>
        <file fileout='python 2.7 byte-compiled' mode='100644' path='/usr/lib/pygtk/2.0/demos/list_store.pyo' group='0' owner='0'/>
        <file fileout='python 2.7 byte-compiled' mode='100644' path='/usr/lib/pygtk/2.0/demos/pixbufs.pyo' group='0' owner='0'/>
        <file fileout='python 2.7 byte-compiled' mode='100644' path='/usr/lib/pygtk/2.0/demos/stock_browser.pyo' group='0' owner='0'/>
        <file fileout='python 2.7 byte-compiled' mode='100644' path='/usr/lib/pygtk/2.0/demos/treemodel.pyo' group='0' owner='0'/>
        <file mode='100644' path='/usr/lib/pygtk/2.0/demos/infobar.py' group='0' owner='0'/>
        <file fileout='a python script, ASCII text executable' mode='100644' path='/usr/lib/pygtk/2.0/demos/dialogs.py' group='0' owner='0'/>
        <file fileout='python 2.7 byte-compiled' mode='100644' path='/usr/lib/pygtk/2.0/demos/dndpixmap.pyo' group='0' owner='0'/>
        <file fileout='a python script, ASCII text executable' mode='100644' path='/usr/lib/pygtk/2.0/demos/sizegroup.py' group='0' owner='0'/>
        <file fileout='python 2.7 byte-compiled' mode='100644' path='/usr/lib/pygtk/2.0/demos/entry_completion.pyc' group='0' owner='0'/>
        <file fileout='python 2.7 byte-compiled' mode='100644' path='/usr/lib/pygtk/2.0/demos/dialogs.pyc' group='0' owner='0'/>
        <file fileout='python 2.7 byte-compiled' mode='100644' path='/usr/lib/pygtk/2.0/demos/pixbufs.pyc' group='0' owner='0'/>
        <file fileout='python 2.7 byte-compiled' mode='100644' path='/usr/lib/pygtk/2.0/demos/__init__.pyo' group='0' owner='0'/>
        <file fileout='a python script, ASCII text executable' mode='100644' path='/usr/lib/pygtk/2.0/demos/print_editor.py' group='0' owner='0'/>
        <file fileout='python 2.7 byte-compiled' mode='100644' path='/usr/lib/pygtk/2.0/demos/ui_manager.pyo' group='0' owner='0'/>
        <file fileout='python 2.7 byte-compiled' mode='100644' path='/usr/lib/pygtk/2.0/demos/dndpixmap.pyc' group='0' owner='0'/>
        <file fileout='a python script, ASCII text executable' mode='100644' path='/usr/lib/pygtk/2.0/demos/ui_manager.py' group='0' owner='0'/>
        <file fileout='python 2.7 byte-compiled' mode='100644' path='/usr/lib/pygtk/2.0/demos/colorsel.pyc' group='0' owner='0'/>
        <file fileout='python 2.7 byte-compiled' mode='100644' path='/usr/lib/pygtk/2.0/demos/textscroll.pyo' group='0' owner='0'/>
        <file fileout='python 2.7 byte-compiled' mode='100644' path='/usr/lib/pygtk/2.0/demos/buttonbox.pyc' group='0' owner='0'/>
        <file fileout='python 2.7 byte-compiled' mode='100644' path='/usr/lib/pygtk/2.0/demos/tooltip.pyo' group='0' owner='0'/>
        <file fileout='python 2.7 byte-compiled' mode='100644' path='/usr/lib/pygtk/2.0/demos/stock_browser.pyc' group='0' owner='0'/>
        <file fileout='python 2.7 byte-compiled' mode='100644' path='/usr/lib/pygtk/2.0/demos/colorsel.pyo' group='0' owner='0'/>
        <file fileout='python 2.7 byte-compiled' mode='100644' path='/usr/lib/pygtk/2.0/demos/print_editor.pyo' group='0' owner='0'/>
        <file fileout='a python script, ASCII text executable' mode='100644' path='/usr/lib/pygtk/2.0/demos/appwindow.py' group='0' owner='0'/>
        <file fileout='python 2.7 byte-compiled' mode='100644' path='/usr/lib/pygtk/2.0/demos/images.pyc' group='0' owner='0'/>
        <file fileout='python 2.7 byte-compiled' mode='100644' path='/usr/lib/pygtk/2.0/demos/expander.pyo' group='0' owner='0'/>
        <file fileout='a python script, ASCII text executable' mode='100644' path='/usr/lib/pygtk/2.0/demos/dnd.py' group='0' owner='0'/>
        <file fileout='a python script, ASCII text executable' mode='100644' path='/usr/lib/pygtk/2.0/demos/stock_browser.py' group='0' owner='0'/>
        <file mode='100644' path='/usr/lib/pygtk/2.0/demos/infobar.pyc' group='0' owner='0'/>
        <file fileout='a python script, ASCII text executable' mode='100644' path='/usr/lib/pygtk/2.0/demos/list_store.py' group='0' owner='0'/>
        <file fileout='python 2.7 byte-compiled' mode='100644' path='/usr/lib/pygtk/2.0/demos/images.pyo' group='0' owner='0'/>
        <file fileout='python 2.7 byte-compiled' mode='100644' path='/usr/lib/pygtk/2.0/demos/dnd.pyc' group='0' owner='0'/>
        <file fileout='a python script, ASCII text executable' mode='100644' path='/usr/lib/pygtk/2.0/demos/statusicon.py' group='0' owner='0'/>
        <file fileout='python 2.7 byte-compiled' mode='100644' path='/usr/lib/pygtk/2.0/demos/dnd.pyo' group='0' owner='0'/>
        <file fileout='a python script, ASCII text executable' mode='100644' path='/usr/lib/pygtk/2.0/demos/menu.py' group='0' owner='0'/>
        <file fileout='JPEG image data, JFIF standard 1.01, comment: &quot;Created with The GIMP&quot;' mode='100644' path='/usr/lib/pygtk/2.0/demos/images/background.jpg' group='0' owner='0'/>
        <file fileout='PNG image data, 48 x 48, 8-bit/color RGBA, non-interlaced' mode='100644' path='/usr/lib/pygtk/2.0/demos/images/gnome-applets.png' group='0' owner='0'/>
        <file fileout='PNG image data, 380 x 287, 8-bit/color RGBA, non-interlaced' mode='100644' path='/usr/lib/pygtk/2.0/demos/images/alphatest.png' group='0' owner='0'/>
        <file fileout='PNG image data, 48 x 48, 8-bit/color RGBA, non-interlaced' mode='100644' path='/usr/lib/pygtk/2.0/demos/images/gnome-gsame.png' group='0' owner='0'/>
        <file fileout='PNG image data, 48 x 48, 8-bit/color RGBA, non-interlaced' mode='100644' path='/usr/lib/pygtk/2.0/demos/images/gnome-calendar.png' group='0' owner='0'/>
        <file fileout='PNG image data, 48 x 48, 8-bit/color RGBA, non-interlaced' mode='100644' path='/usr/lib/pygtk/2.0/demos/images/gnome-gmush.png' group='0' owner='0'/>
        <file fileout='PNG image data, 48 x 48, 8-bit/color RGBA, non-interlaced' mode='100644' path='/usr/lib/pygtk/2.0/demos/images/gnu-keys.png' group='0' owner='0'/>
        <file fileout='GIF image data, version 89a, 80 x 70' mode='100644' path='/usr/lib/pygtk/2.0/demos/images/floppybuddy.gif' group='0' owner='0'/>
        <file fileout='GIF image data, version 89a, 107 x 140' mode='100644' path='/usr/lib/pygtk/2.0/demos/images/gtk-logo-rgb.gif' group='0' owner='0'/>
        <file fileout='PNG image data, 48 x 48, 8-bit/color RGBA, non-interlaced' mode='100644' path='/usr/lib/pygtk/2.0/demos/images/apple-red.png' group='0' owner='0'/>
        <file fileout='PNG image data, 47 x 48, 8-bit/color RGBA, non-interlaced' mode='100644' path='/usr/lib/pygtk/2.0/demos/images/gnome-foot.png' group='0' owner='0'/>
        <file fileout='PNG image data, 48 x 48, 8-bit/color RGBA, non-interlaced' mode='100644' path='/usr/lib/pygtk/2.0/demos/images/gnome-gimp.png' group='0' owner='0'/>
        <file fileout='a python script, ASCII text executable' mode='100644' path='/usr/lib/pygtk/2.0/pygtk-demo.py' group='0' owner='0'/>
        <file fileout='python 2.7 byte-compiled' mode='100644' path='/usr/lib/python2.7/site-packages/gtk-2.0/gtk/_lazyutils.pyo' group='0' owner='0'/>
        <file fileout='python 2.7 byte-compiled' mode='100644' path='/usr/lib/python2.7/site-packages/gtk-2.0/gtk/__init__.pyc' group='0' owner='0'/>
        <file fileout='python 2.7 byte-compiled' mode='100644' path='/usr/lib/python2.7/site-packages/gtk-2.0/gtk/deprecation.pyc' group='0' owner='0'/>
        <file fileout='python 2.7 byte-compiled' mode='100644' path='/usr/lib/python2.7/site-packages/gtk-2.0/gtk/keysyms.pyc' group='0' owner='0'/>
        <file fileout='python 2.7 byte-compiled' mode='100644' path='/usr/lib/python2.7/site-packages/gtk-2.0/gtk/compat.pyc' group='0' owner='0'/>
        <file fileout='python 2.7 byte-compiled' mode='100644' path='/usr/lib/python2.7/site-packages/gtk-2.0/gtk/_lazyutils.pyc' group='0' owner='0'/>
        <file fileout='python 2.7 byte-compiled' mode='100644' path='/usr/lib/python2.7/site-packages/gtk-2.0/gtk/deprecation.pyo' group='0' owner='0'/>
        <file fileout='python 2.7 byte-compiled' mode='100644' path='/usr/lib/python2.7/site-packages/gtk-2.0/gtk/compat.pyo' group='0' owner='0'/>
        <file fileout='Python script, ASCII text executable' mode='100644' path='/usr/lib/python2.7/site-packages/gtk-2.0/gtk/__init__.py' group='0' owner='0'/>
        <file fileout='python 2.7 byte-compiled' mode='100644' path='/usr/lib/python2.7/site-packages/gtk-2.0/gtk/keysyms.pyo' group='0' owner='0'/>
        <file fileout='Python script, ASCII text executable' mode='100644' path='/usr/lib/python2.7/site-packages/gtk-2.0/gtk/_lazyutils.py' group='0' owner='0'/>
        <file fileout='python 2.7 byte-compiled' mode='100644' path='/usr/lib/python2.7/site-packages/gtk-2.0/gtk/__init__.pyo' group='0' owner='0'/>
        <file fileout='Python script, ASCII text executable' mode='100644' path='/usr/lib/python2.7/site-packages/gtk-2.0/gtk/compat.py' group='0' owner='0'/>
        <file fileout='ASCII English text' mode='100644' path='/usr/lib/python2.7/site-packages/gtk-2.0/gtk/keysyms.py' group='0' owner='0'/>
        <file fileout='Python script, ASCII text executable' mode='100644' path='/usr/lib/python2.7/site-packages/gtk-2.0/gtk/deprecation.py' group='0' owner='0'/>
        <file fileout='a /usr/bin/python script, ASCII text executable' mode='100755' path='/usr/bin/pygtk-demo' group='0' owner='0'/>
        <file fileout='POSIX shell script, ASCII text executable' mode='100755' path='/usr/bin/pygtk-codegen-2.0' group='0' owner='0'/>
        <file mode='100644' path='/usr/share/pygtk/2.0/defs/gtk-2.24-types.defs' group='0' owner='0'/>
        <file fileout='ASCII text' mode='100644' path='/usr/share/pygtk/2.0/defs/gtkunixprint-base.defs' group='0' owner='0'/>
        <file fileout='ASCII text' mode='100644' path='/usr/share/pygtk/2.0/defs/gdk-2.18.defs' group='0' owner='0'/>
        <file fileout='ASCII English text' mode='100644' path='/usr/share/pygtk/2.0/defs/gtk-base.defs' group='0' owner='0'/>
        <file fileout='ASCII text' mode='100644' path='/usr/share/pygtk/2.0/defs/gtk-2.14-types.defs' group='0' owner='0'/>
        <file fileout='ASCII text' mode='100644' path='/usr/share/pygtk/2.0/defs/gdk-2.12.defs' group='0' owner='0'/>
        <file mode='100644' path='/usr/share/pygtk/2.0/defs/gdk-2.22.defs' group='0' owner='0'/>
        <file fileout='ASCII text' mode='100644' path='/usr/share/pygtk/2.0/defs/gtk-types.defs' group='0' owner='0'/>
        <file fileout='ASCII text' mode='100644' path='/usr/share/pygtk/2.0/defs/gtk-2.16.defs' group='0' owner='0'/>
        <file fileout='ASCII text' mode='100644' path='/usr/share/pygtk/2.0/defs/gtk-2.16-types.defs' group='0' owner='0'/>
        <file mode='100644' path='/usr/share/pygtk/2.0/defs/gdk-2.24.defs' group='0' owner='0'/>
        <file fileout='ASCII text' mode='100644' path='/usr/share/pygtk/2.0/defs/gtk-base-types.defs' group='0' owner='0'/>
        <file fileout='ASCII text' mode='100644' path='/usr/share/pygtk/2.0/defs/libglade.defs' group='0' owner='0'/>
        <file fileout='ASCII text' mode='100644' path='/usr/share/pygtk/2.0/defs/atk.defs' group='0' owner='0'/>
        <file fileout='ASCII text' mode='100644' path='/usr/share/pygtk/2.0/defs/gtk-2.18-types.defs' group='0' owner='0'/>
        <file fileout='ASCII text' mode='100644' path='/usr/share/pygtk/2.0/defs/gtk-2.14.defs' group='0' owner='0'/>
        <file fileout='ASCII text' mode='100644' path='/usr/share/pygtk/2.0/defs/gtk.defs' group='0' owner='0'/>
        <file fileout='ASCII text' mode='100644' path='/usr/share/pygtk/2.0/defs/gdk-base.defs' group='0' owner='0'/>
        <file fileout='ASCII text' mode='100644' path='/usr/share/pygtk/2.0/defs/gtk-2.10-types.defs' group='0' owner='0'/>
        <file fileout='ASCII text' mode='100644' path='/usr/share/pygtk/2.0/defs/gtkunixprint-2.12.defs' group='0' owner='0'/>
        <file fileout='ASCII text' mode='100644' path='/usr/share/pygtk/2.0/defs/gtk-2.10.defs' group='0' owner='0'/>
        <file fileout='ASCII text' mode='100644' path='/usr/share/pygtk/2.0/defs/gtk-2.18.defs' group='0' owner='0'/>
        <file fileout='ASCII text' mode='100644' path='/usr/share/pygtk/2.0/defs/pangocairo.defs' group='0' owner='0'/>
        <file fileout='ASCII text' mode='100644' path='/usr/share/pygtk/2.0/defs/atk-types.defs' group='0' owner='0'/>
        <file mode='100644' path='/usr/share/pygtk/2.0/defs/gtk-2.22.defs' group='0' owner='0'/>
        <file fileout='ASCII text' mode='100644' path='/usr/share/pygtk/2.0/defs/gtkunixprint-base-types.defs' group='0' owner='0'/>
        <file mode='100644' path='/usr/share/pygtk/2.0/defs/gtk-2.22-types.defs' group='0' owner='0'/>
        <file fileout='ASCII text' mode='100644' path='/usr/share/pygtk/2.0/defs/gtk-2.12.defs' group='0' owner='0'/>
        <file fileout='ASCII C program text' mode='100644' path='/usr/share/pygtk/2.0/defs/pangocairo.override' group='0' owner='0'/>
        <file fileout='ASCII text' mode='100644' path='/usr/share/pygtk/2.0/defs/gtkunixprint-2.14.defs' group='0' owner='0'/>
        <file fileout='ASCII text' mode='100644' path='/usr/share/pygtk/2.0/defs/pango-types.defs' group='0' owner='0'/>
        <file fileout='ASCII text' mode='100644' path='/usr/share/pygtk/2.0/defs/gdk.defs' group='0' owner='0'/>
        <file fileout='ASCII text' mode='100644' path='/usr/share/pygtk/2.0/defs/gtk-extrafuncs.defs' group='0' owner='0'/>
        <file fileout='ASCII text' mode='100644' path='/usr/share/pygtk/2.0/defs/gdk-2.14.defs' group='0' owner='0'/>
        <file fileout='ASCII text' mode='100644' path='/usr/share/pygtk/2.0/defs/gdk-types.defs' group='0' owner='0'/>
        <file mode='100644' path='/usr/share/pygtk/2.0/defs/gtk-2.20-types.defs' group='0' owner='0'/>
        <file mode='100644' path='/usr/share/pygtk/2.0/defs/gtk-2.20.defs' group='0' owner='0'/>
        <file mode='100644' path='/usr/share/pygtk/2.0/defs/gdk-2.20.defs' group='0' owner='0'/>
        <file fileout='ASCII text' mode='100644' path='/usr/share/pygtk/2.0/defs/gtk-2.12-types.defs' group='0' owner='0'/>
        <file fileout='ASCII text' mode='100644' path='/usr/share/pygtk/2.0/defs/gdk-2.16.defs' group='0' owner='0'/>
        <file fileout='ASCII text' mode='100644' path='/usr/share/pygtk/2.0/defs/gdk-base-types.defs' group='0' owner='0'/>
        <file mode='100644' path='/usr/share/pygtk/2.0/defs/gtk-2.24.defs' group='0' owner='0'/>
        <file fileout='ASCII text' mode='100644' path='/usr/share/pygtk/2.0/defs/pango.defs' group='0' owner='0'/>
        <file fileout='ASCII text' mode='100644' path='/usr/share/pygtk/2.0/defs/gdk-2.10.defs' group='0' owner='0'/>
    </subpackage>
    <subpackage name='ignore'>
        <file mode='100600' path='/var/cache/ldconfig/aux-cache' group='0' owner='0'/>
    </subpackage>
</pkgdesc>